{"v":"5.4.3","fr":29.9700012207031,"ip":0,"op":359.00001462237,"w":1000,"h":1000,"nm":"NEW_BTOOTH_LOCK_MASK","ddd":0,"assets":[{"id":"comp_0","layers":[{"ddd":0,"ind":1,"ty":1,"nm":"White Solid 4","sr":1,"ks":{"o":{"a":0,"k":100,"ix":11},"r":{"a":0,"k":0,"ix":10},"p":{"a":0,"k":[500,500,0],"ix":2},"a":{"a":0,"k":[250,250,0],"ix":1},"s":{"a":0,"k":[200,200,100],"ix":6}},"ao":0,"hasMask":true,"masksProperties":[{"inv":false,"mode":"s","pt":{"a":0,"k":{"i":[[131.444,0],[0,-131.444],[-131.444,0],[0,131.444]],"o":[[-131.444,0],[0,131.444],[131.444,0],[0,-131.444]],"v":[[249,10.086],[11,248.086],[249,486.086],[487,248.086]],"c":true},"ix":1},"o":{"a":0,"k":100,"ix":3},"x":{"a":0,"k":0,"ix":4},"nm":"Mask 1"}],"sw":500,"sh":500,"sc":"#ffffff","ip":0,"op":449.000018288145,"st":0,"bm":0},{"ddd":0,"ind":2,"ty":4,"nm":"LockHead Outlines 15","parent":3,"sr":1,"ks":{"o":{"a":0,"k":100,"ix":11},"r":{"a":0,"k":0,"ix":10},"p":{"s":true,"x":{"a":0,"k":74.825,"ix":3},"y":{"a":0,"k":51.767,"ix":4}},"a":{"a":0,"k":[57.643,51.767,0],"ix":1},"s":{"a":1,"k":[{"i":{"x":[0.833,0.833,0.833],"y":[0.833,0.833,0.833]},"o":{"x":[0.167,0.167,0.167],"y":[0.167,0.167,0.167]},"n":["0p833_0p833_0p167_0p167","0p833_0p833_0p167_0p167","0p833_0p833_0p167_0p167"],"t":63,"s":[100,100,100],"e":[87.564,100,100]},{"i":{"x":[0.833,0.833,0.833],"y":[0.833,0.833,0.833]},"o":{"x":[0.167,0.167,0.167],"y":[0.167,0.167,0.167]},"n":["0p833_0p833_0p167_0p167","0p833_0p833_0p167_0p167","0p833_0p833_0p167_0p167"],"t":68,"s":[87.564,100,100],"e":[100,100,100]},{"t":73.000002973351}],"ix":6}},"ao":0,"shapes":[{"ty":"gr","it":[{"ind":0,"ty":"sh","ix":1,"ks":{"a":0,"k":{"i":[[0.82,0],[0,0],[0,3.678],[-0.479,0.068],[0,0],[0,-3.679]],"o":[[0,0],[-0.594,-0.046],[0,-3.679],[0,0],[0.82,0],[0,3.678]],"v":[[4.968,6.688],[4.622,6.709],[4.352,0.124],[4.622,-6.667],[4.968,-6.688],[6.459,0]],"c":true},"ix":2},"nm":"Path 1","mn":"ADBE Vector Shape - Group","hd":false},{"ty":"fl","c":{"a":0,"k":[0.749601721764,0.617707014084,0.459406644106,1],"ix":4},"o":{"a":0,"k":100,"ix":5},"r":1,"bm":0,"nm":"Fill 1","mn":"ADBE Vector Graphic - Fill","hd":false},{"ty":"tr","p":{"a":0,"k":[57.028,51.711],"ix":2},"a":{"a":0,"k":[0,0],"ix":1},"s":{"a":0,"k":[80.304,64.826],"ix":3},"r":{"a":0,"k":0,"ix":6},"o":{"a":0,"k":100,"ix":7},"sk":{"a":0,"k":0,"ix":4},"sa":{"a":0,"k":0,"ix":5},"nm":"Transform"}],"nm":"Group 8","np":2,"cix":2,"bm":0,"ix":1,"mn":"ADBE Vector Group","hd":false},{"ty":"gr","it":[{"ind":0,"ty":"sh","ix":1,"ks":{"a":0,"k":{"i":[[0.82,0],[0,0],[0,3.678],[-0.479,0.068],[0,0],[0,-3.679]],"o":[[0,0],[-0.594,-0.046],[0,-3.679],[0,0],[0.82,0],[0,3.678]],"v":[[4.968,6.688],[4.622,6.709],[4.352,0.124],[4.622,-6.667],[4.968,-6.688],[6.459,0]],"c":true},"ix":2},"nm":"Path 1","mn":"ADBE Vector Shape - Group","hd":false},{"ty":"fl","c":{"a":1,"k":[{"i":{"x":[0.833],"y":[0.833]},"o":{"x":[0.167],"y":[0.167]},"n":["0p833_0p833_0p167_0p167"],"t":63,"s":[1,0.96862745285,0.933333337307,1],"e":[0.939905047417,0.878477871418,0.80937230587,1]},{"i":{"x":[0.833],"y":[0.833]},"o":{"x":[0.167],"y":[0.167]},"n":["0p833_0p833_0p167_0p167"],"t":68,"s":[0.939905047417,0.878477871418,0.80937230587,1],"e":[1,0.96862745285,0.933333337307,1]},{"t":73.000002973351}],"ix":4},"o":{"a":0,"k":100,"ix":5},"r":1,"bm":0,"nm":"Fill 1","mn":"ADBE Vector Graphic - Fill","hd":false},{"ty":"tr","p":{"a":0,"k":[69.575,51.711],"ix":2},"a":{"a":0,"k":[0,0],"ix":1},"s":{"a":0,"k":[80.304,64.826],"ix":3},"r":{"a":0,"k":0,"ix":6},"o":{"a":0,"k":100,"ix":7},"sk":{"a":0,"k":0,"ix":4},"sa":{"a":0,"k":0,"ix":5},"nm":"Transform"}],"nm":"Group 6","np":2,"cix":2,"bm":0,"ix":2,"mn":"ADBE Vector Group","hd":false},{"ty":"gr","it":[{"ind":0,"ty":"sh","ix":1,"ks":{"a":0,"k":{"i":[[3.679,0],[0,0],[0,3.678],[-2.147,0.068],[0,0],[0.034,-5.035]],"o":[[0,0],[-2.664,-0.046],[0,-3.679],[0,0],[3.679,0],[-0.031,4.662]],"v":[[7.101,6.688],[5.548,6.709],[4.338,0.124],[5.548,-6.667],[6.806,-6.684],[13.494,0.004]],"c":true},"ix":2},"nm":"Path 1","mn":"ADBE Vector Shape - Group","hd":false},{"ty":"fl","c":{"a":1,"k":[{"i":{"x":[0.833],"y":[0.833]},"o":{"x":[0.167],"y":[0.167]},"n":["0p833_0p833_0p167_0p167"],"t":63,"s":[0.956188738346,0.885867238045,0.801467180252,1],"e":[0.892340660095,0.792749345303,0.673219621181,1]},{"i":{"x":[0.833],"y":[0.833]},"o":{"x":[0.167],"y":[0.167]},"n":["0p833_0p833_0p167_0p167"],"t":68,"s":[0.892340660095,0.792749345303,0.673219621181,1],"e":[0.956188738346,0.885867238045,0.801467180252,1]},{"t":73.000002973351}],"ix":4},"o":{"a":0,"k":100,"ix":5},"r":1,"bm":0,"nm":"Fill 1","mn":"ADBE Vector Graphic - Fill","hd":false},{"ty":"tr","p":{"a":0,"k":[67.956,51.72],"ix":2},"a":{"a":0,"k":[0,0],"ix":1},"s":{"a":0,"k":[95.696,77.252],"ix":3},"r":{"a":0,"k":0,"ix":6},"o":{"a":0,"k":100,"ix":7},"sk":{"a":0,"k":0,"ix":4},"sa":{"a":0,"k":0,"ix":5},"nm":"Transform"}],"nm":"Group 5","np":2,"cix":2,"bm":0,"ix":3,"mn":"ADBE Vector Group","hd":false},{"ty":"gr","it":[{"ind":0,"ty":"sh","ix":1,"ks":{"a":0,"k":{"i":[[3.679,0],[0,0],[0,3.678],[-3.678,0],[0,0],[0,-3.679]],"o":[[0,0],[-3.678,0],[0,-3.679],[0,0],[3.679,0],[0,3.678]],"v":[[5.759,6.267],[-14.52,6.641],[-18.24,-0.016],[-14.52,-6.735],[5.759,-6.261],[12.447,0.003]],"c":true},"ix":2},"nm":"Path 1","mn":"ADBE Vector Shape - Group","hd":false},{"ty":"fl","c":{"a":1,"k":[{"i":{"x":[0.833],"y":[0.833]},"o":{"x":[0.167],"y":[0.167]},"n":["0p833_0p833_0p167_0p167"],"t":63,"s":[0.809206485748,0.663973331451,0.489664137363,1],"e":[0.860125601292,0.714964032173,0.540740728378,1]},{"i":{"x":[0.833],"y":[0.833]},"o":{"x":[0.167],"y":[0.167]},"n":["0p833_0p833_0p167_0p167"],"t":68,"s":[0.860125601292,0.714964032173,0.540740728378,1],"e":[0.809206485748,0.663973331451,0.489664137363,1]},{"t":73.000002973351}],"ix":4},"o":{"a":0,"k":100,"ix":5},"r":1,"bm":0,"nm":"Fill 1","mn":"ADBE Vector Graphic - Fill","hd":false},{"ty":"tr","p":{"a":0,"k":[67.846,51.76],"ix":2},"a":{"a":0,"k":[0,0],"ix":1},"s":{"a":0,"k":[100,100],"ix":3},"r":{"a":0,"k":0,"ix":6},"o":{"a":0,"k":100,"ix":7},"sk":{"a":0,"k":0,"ix":4},"sa":{"a":0,"k":0,"ix":5},"nm":"Transform"}],"nm":"Group 4","np":2,"cix":2,"bm":0,"ix":4,"mn":"ADBE Vector Group","hd":false}],"ip":34.0000013848484,"op":273.000011119518,"st":36.0000014663101,"bm":0},{"ddd":0,"ind":3,"ty":4,"nm":"LockHead Outlines 13","parent":23,"sr":1,"ks":{"o":{"a":0,"k":100,"ix":11},"r":{"a":0,"k":270,"ix":10},"p":{"s":true,"x":{"a":1,"k":[{"i":{"x":[0.833],"y":[0.833]},"o":{"x":[0.167],"y":[0.167]},"n":["0p833_0p833_0p167_0p167"],"t":34,"s":[121.69],"e":[121.69]},{"i":{"x":[0.833],"y":[0.833]},"o":{"x":[0.167],"y":[0.167]},"n":["0p833_0p833_0p167_0p167"],"t":59,"s":[121.69],"e":[121.69]},{"i":{"x":[0.833],"y":[0.833]},"o":{"x":[0.167],"y":[0.167]},"n":["0p833_0p833_0p167_0p167"],"t":77,"s":[121.69],"e":[121.69]},{"t":106.000004317469}],"ix":3},"y":{"a":1,"k":[{"i":{"x":[0.347],"y":[1]},"o":{"x":[0.363],"y":[0]},"n":["0p347_1_0p363_0"],"t":34,"s":[299.994],"e":[150.404]},{"i":{"x":[0.778],"y":[1]},"o":{"x":[0.632],"y":[0]},"n":["0p778_1_0p632_0"],"t":59,"s":[150.404],"e":[135.404]},{"i":{"x":[0.413],"y":[1]},"o":{"x":[0.181],"y":[0]},"n":["0p413_1_0p181_0"],"t":68,"s":[135.404],"e":[150.404]},{"i":{"x":[0.65],"y":[1]},"o":{"x":[0.574],"y":[0]},"n":["0p65_1_0p574_0"],"t":77,"s":[150.404],"e":[299.994]},{"t":106.000004317469}],"ix":4}},"a":{"a":0,"k":[67.643,47.6,0],"ix":1},"s":{"a":0,"k":[343.438,343.438,100],"ix":6}},"ao":0,"shapes":[{"ty":"gr","it":[{"ind":0,"ty":"sh","ix":1,"ks":{"a":0,"k":{"i":[[3.679,0],[0,0],[0,3.678],[-3.678,0],[0,0],[0,-3.679]],"o":[[0,0],[-3.678,0],[0,-3.679],[0,0],[3.679,0],[0,3.678]],"v":[[7.101,6.688],[-36.07,7.775],[-42.758,-0.043],[-36.07,-7.862],[7.101,-6.688],[13.789,0]],"c":true},"ix":2},"nm":"Path 1","mn":"ADBE Vector Shape - Group","hd":false},{"ty":"fl","c":{"a":0,"k":[0.809206485748,0.663973331451,0.489664137363,1],"ix":4},"o":{"a":0,"k":100,"ix":5},"r":1,"bm":0,"nm":"Fill 1","mn":"ADBE Vector Graphic - Fill","hd":false},{"ty":"tr","p":{"a":0,"k":[67.781,51.782],"ix":2},"a":{"a":0,"k":[0,0],"ix":1},"s":{"a":0,"k":[100,100],"ix":3},"r":{"a":0,"k":0,"ix":6},"o":{"a":0,"k":100,"ix":7},"sk":{"a":0,"k":0,"ix":4},"sa":{"a":0,"k":0,"ix":5},"nm":"Transform"}],"nm":"Group 4","np":2,"cix":2,"bm":0,"ix":1,"mn":"ADBE Vector Group","hd":false}],"ip":34.0000013848484,"op":273.000011119518,"st":36.0000014663101,"bm":0},{"ddd":0,"ind":4,"ty":4,"nm":"Shape Layer 10","parent":23,"sr":1,"ks":{"o":{"a":0,"k":100,"ix":11},"r":{"a":0,"k":0,"ix":10},"p":{"a":0,"k":[112.5,202.819,0],"ix":2},"a":{"a":0,"k":[0,0,0],"ix":1},"s":{"a":0,"k":[71.94,71.94,100],"ix":6}},"ao":0,"shapes":[{"ty":"gr","it":[{"ty":"rc","d":1,"s":{"a":0,"k":[230.312,602.75],"ix":2},"p":{"a":0,"k":[0,0],"ix":3},"r":{"a":0,"k":0,"ix":4},"nm":"Rectangle Path 1","mn":"ADBE Vector Shape - Rect","hd":false},{"ty":"fl","c":{"a":0,"k":[0.705882370472,0.705882370472,0.705882370472,1],"ix":4},"o":{"a":0,"k":100,"ix":5},"r":1,"bm":0,"nm":"Fill 1","mn":"ADBE Vector Graphic - Fill","hd":false},{"ty":"tr","p":{"a":0,"k":[88.156,407.098],"ix":2},"a":{"a":0,"k":[0,0],"ix":1},"s":{"a":0,"k":[100,100],"ix":3},"r":{"a":0,"k":0,"ix":6},"o":{"a":0,"k":100,"ix":7},"sk":{"a":0,"k":0,"ix":4},"sa":{"a":0,"k":0,"ix":5},"nm":"Transform"}],"nm":"Rectangle 1","np":2,"cix":2,"bm":0,"ix":1,"mn":"ADBE Vector Group","hd":false}],"ip":-3.00000012219251,"op":398.000016210872,"st":38.0000015477717,"bm":0},{"ddd":0,"ind":5,"ty":4,"nm":"Shape Layer 7","parent":23,"sr":1,"ks":{"o":{"a":0,"k":100,"ix":11},"r":{"a":0,"k":0,"ix":10},"p":{"a":0,"k":[112.5,57.5,0],"ix":2},"a":{"a":0,"k":[0,0,0],"ix":1},"s":{"a":0,"k":[71.94,71.94,100],"ix":6}},"ao":0,"shapes":[{"ty":"gr","it":[{"ty":"rc","d":1,"s":{"a":0,"k":[230.312,602.75],"ix":2},"p":{"a":0,"k":[0,0],"ix":3},"r":{"a":0,"k":0,"ix":4},"nm":"Rectangle Path 1","mn":"ADBE Vector Shape - Rect","hd":false},{"ty":"fl","c":{"a":0,"k":[0.705882370472,0.705882370472,0.705882370472,1],"ix":4},"o":{"a":0,"k":100,"ix":5},"r":1,"bm":0,"nm":"Fill 1","mn":"ADBE Vector Graphic - Fill","hd":false},{"ty":"tr","p":{"a":0,"k":[88.156,407.098],"ix":2},"a":{"a":0,"k":[0,0],"ix":1},"s":{"a":0,"k":[100,100],"ix":3},"r":{"a":0,"k":0,"ix":6},"o":{"a":0,"k":100,"ix":7},"sk":{"a":0,"k":0,"ix":4},"sa":{"a":0,"k":0,"ix":5},"nm":"Transform"}],"nm":"Rectangle 1","np":2,"cix":2,"bm":0,"ix":1,"mn":"ADBE Vector Group","hd":false}],"ip":-3.00000012219251,"op":34.0000013848484,"st":38.0000015477717,"bm":0},{"ddd":0,"ind":6,"ty":4,"nm":"Shape Layer 4","parent":23,"sr":1,"ks":{"o":{"a":0,"k":100,"ix":11},"r":{"a":0,"k":154,"ix":10},"p":{"a":0,"k":[41.403,116.411,0],"ix":2},"a":{"a":0,"k":[304,61.252,0],"ix":1},"s":{"a":0,"k":[27.185,27.185,100],"ix":6}},"ao":0,"shapes":[{"ty":"gr","it":[{"ind":0,"ty":"sh","ix":1,"ks":{"a":0,"k":{"i":[[0,0],[0,0]],"o":[[0,0],[0,0]],"v":[[303,29],[363.5,-15]],"c":false},"ix":2},"nm":"Path 1","mn":"ADBE Vector Shape - Group","hd":false},{"ty":"tm","s":{"a":1,"k":[{"i":{"x":[0.547],"y":[1]},"o":{"x":[0.37],"y":[0]},"n":["0p547_1_0p37_0"],"t":242.986,"s":[0],"e":[100]},{"t":249.080010145236}],"ix":1},"e":{"a":1,"k":[{"i":{"x":[0.6],"y":[1]},"o":{"x":[0.539],"y":[0]},"n":["0p6_1_0p539_0"],"t":246.394,"s":[0],"e":[100]},{"t":253.163760311571}],"ix":2},"o":{"a":0,"k":0,"ix":3},"m":1,"ix":2,"nm":"Trim Paths 1","mn":"ADBE Vector Filter - Trim","hd":false},{"ty":"st","c":{"a":0,"k":[0.329411774874,0.839215695858,0.784313738346,1],"ix":3},"o":{"a":1,"k":[{"i":{"x":[0.833],"y":[0.833]},"o":{"x":[0.167],"y":[0.167]},"n":["0p833_0p833_0p167_0p167"],"t":243,"s":[100],"e":[1]},{"t":251.00001022344}],"ix":4},"w":{"a":0,"k":9,"ix":5},"lc":1,"lj":1,"ml":4,"ml2":{"a":0,"k":4,"ix":8},"bm":0,"nm":"Stroke 1","mn":"ADBE Vector Graphic - Stroke","hd":false},{"ty":"fl","c":{"a":0,"k":[0.890196018593,0.890196018593,0.890196018593,1],"ix":4},"o":{"a":0,"k":100,"ix":5},"r":1,"bm":0,"nm":"Fill 1","mn":"ADBE Vector Graphic - Fill","hd":false},{"ty":"tr","p":{"a":0,"k":[0,18.504],"ix":2},"a":{"a":0,"k":[0,0],"ix":1},"s":{"a":0,"k":[100,100],"ix":3},"r":{"a":0,"k":0,"ix":6},"o":{"a":0,"k":100,"ix":7},"sk":{"a":0,"k":0,"ix":4},"sa":{"a":0,"k":0,"ix":5},"nm":"Transform"}],"nm":"Shape 2","np":4,"cix":2,"bm":0,"ix":1,"mn":"ADBE Vector Group","hd":false},{"ty":"gr","it":[{"ind":0,"ty":"sh","ix":1,"ks":{"a":0,"k":{"i":[[0,0],[0,0]],"o":[[0,0],[0,0]],"v":[[314.707,53.163],[375.207,9.163]],"c":false},"ix":2},"nm":"Path 1","mn":"ADBE Vector Shape - Group","hd":false},{"ty":"tm","s":{"a":1,"k":[{"i":{"x":[0.547],"y":[1]},"o":{"x":[0.37],"y":[0]},"n":["0p547_1_0p37_0"],"t":242.986,"s":[0],"e":[100]},{"t":249.080010145236}],"ix":1},"e":{"a":1,"k":[{"i":{"x":[0.6],"y":[1]},"o":{"x":[0.539],"y":[0]},"n":["0p6_1_0p539_0"],"t":246.394,"s":[0],"e":[100]},{"t":253.163760311571}],"ix":2},"o":{"a":0,"k":0,"ix":3},"m":1,"ix":2,"nm":"Trim Paths 1","mn":"ADBE Vector Filter - Trim","hd":false},{"ty":"st","c":{"a":0,"k":[0.329411774874,0.839215695858,0.784313738346,1],"ix":3},"o":{"a":1,"k":[{"i":{"x":[0.833],"y":[0.833]},"o":{"x":[0.167],"y":[0.167]},"n":["0p833_0p833_0p167_0p167"],"t":243,"s":[100],"e":[1]},{"t":251.00001022344}],"ix":4},"w":{"a":0,"k":9,"ix":5},"lc":1,"lj":1,"ml":4,"ml2":{"a":0,"k":4,"ix":8},"bm":0,"nm":"Stroke 1","mn":"ADBE Vector Graphic - Stroke","hd":false},{"ty":"fl","c":{"a":0,"k":[0.890196018593,0.890196018593,0.890196018593,1],"ix":4},"o":{"a":0,"k":100,"ix":5},"r":1,"bm":0,"nm":"Fill 1","mn":"ADBE Vector Graphic - Fill","hd":false},{"ty":"tr","p":{"a":0,"k":[336.441,84.809],"ix":2},"a":{"a":0,"k":[334,28],"ix":1},"s":{"a":0,"k":[100,100],"ix":3},"r":{"a":0,"k":62,"ix":6},"o":{"a":0,"k":100,"ix":7},"sk":{"a":0,"k":0,"ix":4},"sa":{"a":0,"k":0,"ix":5},"nm":"Transform"}],"nm":"Shape 1","np":4,"cix":2,"bm":0,"ix":2,"mn":"ADBE Vector Group","hd":false}],"ip":229.000009327361,"op":349.000014215061,"st":229.000009327361,"bm":0},{"ddd":0,"ind":7,"ty":4,"nm":"Lock Outlines 3","parent":23,"sr":1,"ks":{"o":{"a":0,"k":100,"ix":11},"r":{"a":0,"k":0,"ix":10},"p":{"s":true,"x":{"a":0,"k":112.5,"ix":3},"y":{"a":0,"k":57.5,"ix":4}},"a":{"a":0,"k":[112.5,57.5,0],"ix":1},"s":{"a":0,"k":[100,100,100],"ix":6}},"ao":0,"shapes":[{"ty":"gr","it":[{"ind":0,"ty":"sh","ix":1,"ks":{"a":0,"k":{"i":[[0,0],[-3.095,0],[5.704,0]],"o":[[0,0],[5.158,0],[-4.308,0]],"v":[[136.347,60.716],[141.565,60.777],[141.019,52.585]],"c":false},"ix":2},"nm":"Path 1","mn":"ADBE Vector Shape - Group","hd":false},{"ty":"st","c":{"a":0,"k":[0.168627455831,0.168627455831,0.168627455831,1],"ix":3},"o":{"a":0,"k":100,"ix":4},"w":{"a":0,"k":2,"ix":5},"lc":1,"lj":1,"ml":4,"ml2":{"a":0,"k":4,"ix":8},"bm":0,"nm":"Stroke 1","mn":"ADBE Vector Graphic - Stroke","hd":false},{"ty":"tr","p":{"a":0,"k":[-2,0],"ix":2},"a":{"a":0,"k":[0,0],"ix":1},"s":{"a":0,"k":[100,100],"ix":3},"r":{"a":0,"k":0,"ix":6},"o":{"a":0,"k":100,"ix":7},"sk":{"a":0,"k":0,"ix":4},"sa":{"a":0,"k":0,"ix":5},"nm":"Transform"}],"nm":"Shape 1","np":2,"cix":2,"bm":0,"ix":1,"mn":"ADBE Vector Group","hd":false},{"ty":"gr","it":[{"ind":0,"ty":"sh","ix":1,"ks":{"a":0,"k":{"i":[[0,0],[0,0],[1.163,0],[0,0],[0,-1.163],[0,0],[-1.164,0],[0,0],[0,1.163],[0,0]],"o":[[0,0],[0,-1.163],[0,0],[-1.164,0],[0,0],[0,1.163],[0,0],[1.163,0],[0,0],[0,0]],"v":[[1.977,0.279],[1.977,-5.326],[-0.13,-7.432],[-4.897,-7.432],[-7.004,-5.326],[-7.004,1.769],[-4.897,3.875],[-0.13,3.875],[1.977,1.769],[1.977,1.286]],"c":true},"ix":2},"nm":"Path 2","mn":"ADBE Vector Shape - Group","hd":false},{"ty":"mm","mm":1,"nm":"Merge Paths 1","mn":"ADBE Vector Filter - Merge","hd":false},{"ty":"fl","c":{"a":0,"k":[0.169000004787,0.169000004787,0.169000004787,1],"ix":4},"o":{"a":0,"k":100,"ix":5},"r":1,"bm":0,"nm":"Fill 1","mn":"ADBE Vector Graphic - Fill","hd":false},{"ty":"tr","p":{"a":0,"k":[134.57,58.975],"ix":2},"a":{"a":0,"k":[0,0],"ix":1},"s":{"a":0,"k":[100,100],"ix":3},"r":{"a":0,"k":0,"ix":6},"o":{"a":0,"k":100,"ix":7},"sk":{"a":0,"k":0,"ix":4},"sa":{"a":0,"k":0,"ix":5},"nm":"Transform"}],"nm":"Group 2","np":3,"cix":2,"bm":0,"ix":2,"mn":"ADBE Vector Group","hd":false}],"ip":-3.00000012219251,"op":398.000016210872,"st":38.0000015477717,"bm":0},{"ddd":0,"ind":8,"ty":4,"nm":"Shape Layer 15","parent":23,"td":1,"sr":1,"ks":{"o":{"a":0,"k":100,"ix":11},"r":{"a":0,"k":0,"ix":10},"p":{"a":0,"k":[112.5,57.5,0],"ix":2},"a":{"a":0,"k":[0,0,0],"ix":1},"s":{"a":0,"k":[24.271,24.271,100],"ix":6}},"ao":0,"shapes":[{"ty":"gr","it":[{"d":1,"ty":"el","s":{"a":0,"k":[123.684,123.684],"ix":2},"p":{"a":0,"k":[0,0],"ix":3},"nm":"Ellipse Path 1","mn":"ADBE Vector Shape - Ellipse","hd":false},{"ty":"st","c":{"a":0,"k":[1,1,1,1],"ix":3},"o":{"a":0,"k":100,"ix":4},"w":{"a":0,"k":2,"ix":5},"lc":1,"lj":1,"ml":4,"ml2":{"a":0,"k":4,"ix":8},"bm":0,"nm":"Stroke 1","mn":"ADBE Vector Graphic - Stroke","hd":false},{"ty":"fl","c":{"a":0,"k":[0.890196018593,0.890196018593,0.890196018593,1],"ix":4},"o":{"a":0,"k":100,"ix":5},"r":1,"bm":0,"nm":"Fill 1","mn":"ADBE Vector Graphic - Fill","hd":false},{"ty":"tr","p":{"a":0,"k":[96.516,-1.928],"ix":2},"a":{"a":0,"k":[0,0],"ix":1},"s":{"a":0,"k":[100,100],"ix":3},"r":{"a":0,"k":0,"ix":6},"o":{"a":0,"k":100,"ix":7},"sk":{"a":0,"k":0,"ix":4},"sa":{"a":0,"k":0,"ix":5},"nm":"Transform"}],"nm":"Ellipse 1","np":3,"cix":2,"bm":0,"ix":1,"mn":"ADBE Vector Group","hd":false}],"ip":0,"op":750.000030548126,"st":0,"bm":0},{"ddd":0,"ind":9,"ty":4,"nm":"Shape Layer 3","parent":6,"tt":1,"sr":1,"ks":{"o":{"a":0,"k":100,"ix":11},"r":{"a":0,"k":-118,"ix":10},"p":{"a":0,"k":[148.127,-8.812,0],"ix":2},"a":{"a":0,"k":[304,61.252,0],"ix":1},"s":{"a":0,"k":[100,100,100],"ix":6}},"ao":0,"shapes":[{"ty":"gr","it":[{"ind":0,"ty":"sh","ix":1,"ks":{"a":0,"k":{"i":[[0,0],[0,0]],"o":[[0,0],[0,0]],"v":[[303,29],[363.5,-15]],"c":false},"ix":2},"nm":"Path 1","mn":"ADBE Vector Shape - Group","hd":false},{"ty":"tm","s":{"a":1,"k":[{"i":{"x":[0.547],"y":[1]},"o":{"x":[0.37],"y":[0]},"n":["0p547_1_0p37_0"],"t":242.986,"s":[0],"e":[100]},{"t":249.080010145236}],"ix":1},"e":{"a":1,"k":[{"i":{"x":[0.6],"y":[1]},"o":{"x":[0.539],"y":[0]},"n":["0p6_1_0p539_0"],"t":246.394,"s":[0],"e":[100]},{"t":253.163760311571}],"ix":2},"o":{"a":0,"k":0,"ix":3},"m":1,"ix":2,"nm":"Trim Paths 1","mn":"ADBE Vector Filter - Trim","hd":false},{"ty":"st","c":{"a":0,"k":[0.329411774874,0.839215695858,0.784313738346,1],"ix":3},"o":{"a":1,"k":[{"i":{"x":[0.833],"y":[0.833]},"o":{"x":[0.167],"y":[0.167]},"n":["0p833_0p833_0p167_0p167"],"t":243,"s":[100],"e":[1]},{"t":251.00001022344}],"ix":4},"w":{"a":0,"k":9,"ix":5},"lc":1,"lj":1,"ml":4,"ml2":{"a":0,"k":4,"ix":8},"bm":0,"nm":"Stroke 1","mn":"ADBE Vector Graphic - Stroke","hd":false},{"ty":"fl","c":{"a":0,"k":[0.890196018593,0.890196018593,0.890196018593,1],"ix":4},"o":{"a":0,"k":100,"ix":5},"r":1,"bm":0,"nm":"Fill 1","mn":"ADBE Vector Graphic - Fill","hd":false},{"ty":"tr","p":{"a":0,"k":[0,18.504],"ix":2},"a":{"a":0,"k":[0,0],"ix":1},"s":{"a":0,"k":[100,100],"ix":3},"r":{"a":0,"k":0,"ix":6},"o":{"a":0,"k":100,"ix":7},"sk":{"a":0,"k":0,"ix":4},"sa":{"a":0,"k":0,"ix":5},"nm":"Transform"}],"nm":"Shape 2","np":4,"cix":2,"bm":0,"ix":1,"mn":"ADBE Vector Group","hd":false},{"ty":"gr","it":[{"ind":0,"ty":"sh","ix":1,"ks":{"a":0,"k":{"i":[[0,0],[0,0]],"o":[[0,0],[0,0]],"v":[[314.707,53.163],[375.207,9.163]],"c":false},"ix":2},"nm":"Path 1","mn":"ADBE Vector Shape - Group","hd":false},{"ty":"tm","s":{"a":1,"k":[{"i":{"x":[0.547],"y":[1]},"o":{"x":[0.37],"y":[0]},"n":["0p547_1_0p37_0"],"t":242.986,"s":[0],"e":[100]},{"t":249.080010145236}],"ix":1},"e":{"a":1,"k":[{"i":{"x":[0.6],"y":[1]},"o":{"x":[0.539],"y":[0]},"n":["0p6_1_0p539_0"],"t":246.394,"s":[0],"e":[100]},{"t":253.163760311571}],"ix":2},"o":{"a":0,"k":0,"ix":3},"m":1,"ix":2,"nm":"Trim Paths 1","mn":"ADBE Vector Filter - Trim","hd":false},{"ty":"st","c":{"a":0,"k":[0.329411774874,0.839215695858,0.784313738346,1],"ix":3},"o":{"a":1,"k":[{"i":{"x":[0.833],"y":[0.833]},"o":{"x":[0.167],"y":[0.167]},"n":["0p833_0p833_0p167_0p167"],"t":243,"s":[100],"e":[1]},{"t":251.00001022344}],"ix":4},"w":{"a":0,"k":9,"ix":5},"lc":1,"lj":1,"ml":4,"ml2":{"a":0,"k":4,"ix":8},"bm":0,"nm":"Stroke 1","mn":"ADBE Vector Graphic - Stroke","hd":false},{"ty":"fl","c":{"a":0,"k":[0.890196018593,0.890196018593,0.890196018593,1],"ix":4},"o":{"a":0,"k":100,"ix":5},"r":1,"bm":0,"nm":"Fill 1","mn":"ADBE Vector Graphic - Fill","hd":false},{"ty":"tr","p":{"a":0,"k":[336.441,84.809],"ix":2},"a":{"a":0,"k":[334,28],"ix":1},"s":{"a":0,"k":[100,100],"ix":3},"r":{"a":0,"k":62,"ix":6},"o":{"a":0,"k":100,"ix":7},"sk":{"a":0,"k":0,"ix":4},"sa":{"a":0,"k":0,"ix":5},"nm":"Transform"}],"nm":"Shape 1","np":4,"cix":2,"bm":0,"ix":2,"mn":"ADBE Vector Group","hd":false}],"ip":229.000009327361,"op":349.000014215061,"st":229.000009327361,"bm":0},{"ddd":0,"ind":10,"ty":4,"nm":"Shape Layer 14","parent":23,"td":1,"sr":1,"ks":{"o":{"a":0,"k":100,"ix":11},"r":{"a":0,"k":0,"ix":10},"p":{"a":0,"k":[112.5,57.5,0],"ix":2},"a":{"a":0,"k":[0,0,0],"ix":1},"s":{"a":0,"k":[24.271,24.271,100],"ix":6}},"ao":0,"shapes":[{"ty":"gr","it":[{"d":1,"ty":"el","s":{"a":0,"k":[123.684,123.684],"ix":2},"p":{"a":0,"k":[0,0],"ix":3},"nm":"Ellipse Path 1","mn":"ADBE Vector Shape - Ellipse","hd":false},{"ty":"st","c":{"a":0,"k":[1,1,1,1],"ix":3},"o":{"a":0,"k":100,"ix":4},"w":{"a":0,"k":2,"ix":5},"lc":1,"lj":1,"ml":4,"ml2":{"a":0,"k":4,"ix":8},"bm":0,"nm":"Stroke 1","mn":"ADBE Vector Graphic - Stroke","hd":false},{"ty":"fl","c":{"a":0,"k":[0.890196018593,0.890196018593,0.890196018593,1],"ix":4},"o":{"a":0,"k":100,"ix":5},"r":1,"bm":0,"nm":"Fill 1","mn":"ADBE Vector Graphic - Fill","hd":false},{"ty":"tr","p":{"a":0,"k":[96.516,-1.928],"ix":2},"a":{"a":0,"k":[0,0],"ix":1},"s":{"a":0,"k":[100,100],"ix":3},"r":{"a":0,"k":0,"ix":6},"o":{"a":0,"k":100,"ix":7},"sk":{"a":0,"k":0,"ix":4},"sa":{"a":0,"k":0,"ix":5},"nm":"Transform"}],"nm":"Ellipse 1","np":3,"cix":2,"bm":0,"ix":1,"mn":"ADBE Vector Group","hd":false}],"ip":0,"op":750.000030548126,"st":0,"bm":0},{"ddd":0,"ind":11,"ty":4,"nm":"LockHead Outlines 21","parent":23,"tt":1,"sr":1,"ks":{"o":{"a":0,"k":100,"ix":11},"r":{"a":0,"k":0,"ix":10},"p":{"s":true,"x":{"a":0,"k":136.119,"ix":3},"y":{"a":0,"k":67.514,"ix":4}},"a":{"a":0,"k":[74.757,51.728,0],"ix":1},"s":{"a":0,"k":[73.532,73.532,100],"ix":6}},"ao":0,"shapes":[{"ty":"gr","it":[{"ty":"fl","c":{"a":0,"k":[1,1,1,1],"ix":4},"o":{"a":1,"k":[{"i":{"x":[0],"y":[1]},"o":{"x":[0.167],"y":[0.167]},"n":["0_1_0p167_0p167"],"t":199.061,"s":[0],"e":[100]},{"i":{"x":[0.683],"y":[1.466]},"o":{"x":[0.35],"y":[0]},"n":["0p683_1p466_0p35_0"],"t":205.061,"s":[100],"e":[100]},{"t":206.000008390552}],"ix":5},"r":1,"bm":0,"nm":"Fill 1","mn":"ADBE Vector Graphic - Fill","hd":false},{"ty":"tr","p":{"a":0,"k":[74.757,51.798],"ix":2},"a":{"a":0,"k":[0,0],"ix":1},"s":{"a":0,"k":[53.764,51.454],"ix":3},"r":{"a":0,"k":0,"ix":6},"o":{"a":0,"k":100,"ix":7},"sk":{"a":0,"k":0,"ix":4},"sa":{"a":0,"k":0,"ix":5},"nm":"Transform"}],"nm":"Group 4","np":1,"cix":2,"bm":0,"ix":1,"mn":"ADBE Vector Group","hd":false},{"ty":"gr","it":[{"ind":0,"ty":"sh","ix":1,"ks":{"a":0,"k":{"i":[[0,-2.69],[2.69,0],[0,2.69],[-2.691,0]],"o":[[0,2.69],[-2.691,0],[0,-2.69],[2.69,0]],"v":[[4.872,0],[0.001,4.872],[-4.872,0],[0.001,-4.872]],"c":true},"ix":2},"nm":"Path 1","mn":"ADBE Vector Shape - Group","hd":false},{"ty":"fl","c":{"a":0,"k":[0,0.768627464771,1,1],"ix":4},"o":{"a":1,"k":[{"i":{"x":[0],"y":[1]},"o":{"x":[0.167],"y":[0.167]},"n":["0_1_0p167_0p167"],"t":199.061,"s":[0],"e":[100]},{"t":212.000008634937}],"ix":5},"r":1,"bm":0,"nm":"Fill 1","mn":"ADBE Vector Graphic - Fill","hd":false},{"ty":"tr","p":{"a":0,"k":[74.757,51.728],"ix":2},"a":{"a":0,"k":[0,0],"ix":1},"s":{"a":0,"k":[100,100],"ix":3},"r":{"a":0,"k":0,"ix":6},"o":{"a":0,"k":100,"ix":7},"sk":{"a":0,"k":0,"ix":4},"sa":{"a":0,"k":0,"ix":5},"nm":"Transform"}],"nm":"Group 3","np":2,"cix":2,"bm":0,"ix":2,"mn":"ADBE Vector Group","hd":false}],"ip":199.000008105436,"op":365.000014866755,"st":148.000006028164,"bm":0},{"ddd":0,"ind":12,"ty":4,"nm":"Shape Layer 18","parent":11,"sr":1,"ks":{"o":{"a":0,"k":100,"ix":11},"r":{"a":0,"k":0,"ix":10},"p":{"a":0,"k":[42.142,38.275,0],"ix":2},"a":{"a":0,"k":[0,0,0],"ix":1},"s":{"a":0,"k":[33.266,33.266,100],"ix":6}},"ao":0,"shapes":[{"ty":"gr","it":[{"d":1,"ty":"el","s":{"a":0,"k":[123.684,123.684],"ix":2},"p":{"a":0,"k":[0,0],"ix":3},"nm":"Ellipse Path 1","mn":"ADBE Vector Shape - Ellipse","hd":false},{"ty":"fl","c":{"a":0,"k":[0.76845896244,1,1,1],"ix":4},"o":{"a":1,"k":[{"i":{"x":[0.154],"y":[1]},"o":{"x":[0.478],"y":[0]},"n":["0p154_1_0p478_0"],"t":199,"s":[0],"e":[100]},{"t":203.000008268359}],"ix":5},"r":1,"bm":0,"nm":"Fill 1","mn":"ADBE Vector Graphic - Fill","hd":false},{"ty":"tr","p":{"a":0,"k":[96.516,-1.928],"ix":2},"a":{"a":0,"k":[0,0],"ix":1},"s":{"a":0,"k":[100,100],"ix":3},"r":{"a":0,"k":0,"ix":6},"o":{"a":0,"k":100,"ix":7},"sk":{"a":0,"k":0,"ix":4},"sa":{"a":0,"k":0,"ix":5},"nm":"Transform"}],"nm":"Ellipse 1","np":2,"cix":2,"bm":0,"ix":1,"mn":"ADBE Vector Group","hd":false}],"ip":199.000008105436,"op":365.000014866755,"st":96.0000039101602,"bm":0},{"ddd":0,"ind":13,"ty":4,"nm":"Shape Layer 13","td":1,"sr":1,"ks":{"o":{"a":0,"k":100,"ix":11},"r":{"a":0,"k":0,"ix":10},"p":{"a":0,"k":[500,500,0],"ix":2},"a":{"a":0,"k":[0,0,0],"ix":1},"s":{"a":0,"k":[100,100,100],"ix":6}},"ao":0,"shapes":[{"ty":"gr","it":[{"d":1,"ty":"el","s":{"a":0,"k":[123.684,123.684],"ix":2},"p":{"a":0,"k":[0,0],"ix":3},"nm":"Ellipse Path 1","mn":"ADBE Vector Shape - Ellipse","hd":false},{"ty":"st","c":{"a":0,"k":[1,1,1,1],"ix":3},"o":{"a":0,"k":100,"ix":4},"w":{"a":0,"k":2,"ix":5},"lc":1,"lj":1,"ml":4,"ml2":{"a":0,"k":4,"ix":8},"bm":0,"nm":"Stroke 1","mn":"ADBE Vector Graphic - Stroke","hd":false},{"ty":"fl","c":{"a":0,"k":[0.890196018593,0.890196018593,0.890196018593,1],"ix":4},"o":{"a":0,"k":100,"ix":5},"r":1,"bm":0,"nm":"Fill 1","mn":"ADBE Vector Graphic - Fill","hd":false},{"ty":"tr","p":{"a":0,"k":[96.516,-1.928],"ix":2},"a":{"a":0,"k":[0,0],"ix":1},"s":{"a":0,"k":[100,100],"ix":3},"r":{"a":0,"k":0,"ix":6},"o":{"a":0,"k":100,"ix":7},"sk":{"a":0,"k":0,"ix":4},"sa":{"a":0,"k":0,"ix":5},"nm":"Transform"}],"nm":"Ellipse 1","np":3,"cix":2,"bm":0,"ix":1,"mn":"ADBE Vector Group","hd":false}],"ip":0,"op":750.000030548126,"st":0,"bm":0},{"ddd":0,"ind":14,"ty":4,"nm":"LockHead Outlines 20","parent":23,"tt":1,"sr":1,"ks":{"o":{"a":0,"k":100,"ix":11},"r":{"a":0,"k":0,"ix":10},"p":{"s":true,"x":{"a":0,"k":136.119,"ix":3},"y":{"a":0,"k":46.519,"ix":4}},"a":{"a":0,"k":[74.757,51.728,0],"ix":1},"s":{"a":0,"k":[73.532,73.532,100],"ix":6}},"ao":0,"shapes":[{"ty":"gr","it":[{"ind":0,"ty":"sh","ix":1,"ks":{"a":0,"k":{"i":[[0,-2.69],[2.69,0],[0,2.69],[-2.691,0]],"o":[[0,2.69],[-2.691,0],[0,-2.69],[2.69,0]],"v":[[4.872,0],[0.001,4.872],[-4.872,0],[0.001,-4.872]],"c":true},"ix":2},"nm":"Path 1","mn":"ADBE Vector Shape - Group","hd":false},{"ty":"fl","c":{"a":0,"k":[0.937254965305,0.078431375325,0.078431375325,1],"ix":4},"o":{"a":1,"k":[{"i":{"x":[0],"y":[1]},"o":{"x":[0.167],"y":[0.167]},"n":["0_1_0p167_0p167"],"t":151.061,"s":[0],"e":[100]},{"i":{"x":[0.833],"y":[0.833]},"o":{"x":[0.758],"y":[0]},"n":["0p833_0p833_0p758_0"],"t":157.061,"s":[100],"e":[0]},{"t":165.061256723083}],"ix":5},"r":1,"bm":0,"nm":"Fill 1","mn":"ADBE Vector Graphic - Fill","hd":false},{"ty":"tr","p":{"a":0,"k":[74.757,51.728],"ix":2},"a":{"a":0,"k":[0,0],"ix":1},"s":{"a":0,"k":[100,100],"ix":3},"r":{"a":0,"k":0,"ix":6},"o":{"a":0,"k":100,"ix":7},"sk":{"a":0,"k":0,"ix":4},"sa":{"a":0,"k":0,"ix":5},"nm":"Transform"}],"nm":"Group 3","np":2,"cix":2,"bm":0,"ix":1,"mn":"ADBE Vector Group","hd":false},{"ty":"st","c":{"a":0,"k":[1,0.646553277969,0.646553277969,1],"ix":3},"o":{"a":1,"k":[{"i":{"x":[0.684],"y":[1.009]},"o":{"x":[0.167],"y":[0.167]},"n":["0p684_1p009_0p167_0p167"],"t":151,"s":[0],"e":[100]},{"i":{"x":[0.821],"y":[0.962]},"o":{"x":[0.711],"y":[0.021]},"n":["0p821_0p962_0p711_0p021"],"t":158,"s":[100],"e":[0]},{"t":165.000006720588}],"ix":4},"w":{"a":0,"k":110,"ix":5},"lc":1,"lj":1,"ml":4,"ml2":{"a":0,"k":4,"ix":8},"bm":1,"nm":"Stroke 1","mn":"ADBE Vector Graphic - Stroke","hd":false}],"ip":151.000006150356,"op":168.00000684278,"st":100.000004073084,"bm":0},{"ddd":0,"ind":15,"ty":4,"nm":"Shape Layer 17","sr":1,"ks":{"o":{"a":0,"k":100,"ix":11},"r":{"a":0,"k":0,"ix":10},"p":{"a":0,"k":[500,500,0],"ix":2},"a":{"a":0,"k":[0,0,0],"ix":1},"s":{"a":0,"k":[100,100,100],"ix":6}},"ao":0,"shapes":[{"ty":"gr","it":[{"d":1,"ty":"el","s":{"a":0,"k":[123.684,123.684],"ix":2},"p":{"a":0,"k":[0,0],"ix":3},"nm":"Ellipse Path 1","mn":"ADBE Vector Shape - Ellipse","hd":false},{"ty":"fl","c":{"a":0,"k":[0.996078431606,0.658823549747,0.658823549747,1],"ix":4},"o":{"a":1,"k":[{"i":{"x":[0.154],"y":[1]},"o":{"x":[0.478],"y":[0]},"n":["0p154_1_0p478_0"],"t":151,"s":[0],"e":[100]},{"i":{"x":[0.561],"y":[1]},"o":{"x":[0.92],"y":[0]},"n":["0p561_1_0p92_0"],"t":155,"s":[100],"e":[0]},{"t":165.000006720588}],"ix":5},"r":1,"bm":0,"nm":"Fill 1","mn":"ADBE Vector Graphic - Fill","hd":false},{"ty":"tr","p":{"a":0,"k":[96.516,-1.928],"ix":2},"a":{"a":0,"k":[0,0],"ix":1},"s":{"a":0,"k":[100,100],"ix":3},"r":{"a":0,"k":0,"ix":6},"o":{"a":0,"k":100,"ix":7},"sk":{"a":0,"k":0,"ix":4},"sa":{"a":0,"k":0,"ix":5},"nm":"Transform"}],"nm":"Ellipse 1","np":2,"cix":2,"bm":0,"ix":1,"mn":"ADBE Vector Group","hd":false}],"ip":151.000006150356,"op":168.00000684278,"st":48.0000019550801,"bm":0},{"ddd":0,"ind":16,"ty":4,"nm":"Shape Layer 12","td":1,"sr":1,"ks":{"o":{"a":0,"k":100,"ix":11},"r":{"a":0,"k":0,"ix":10},"p":{"a":0,"k":[500,500,0],"ix":2},"a":{"a":0,"k":[0,0,0],"ix":1},"s":{"a":0,"k":[100,100,100],"ix":6}},"ao":0,"shapes":[{"ty":"gr","it":[{"d":1,"ty":"el","s":{"a":0,"k":[123.684,123.684],"ix":2},"p":{"a":0,"k":[0,0],"ix":3},"nm":"Ellipse Path 1","mn":"ADBE Vector Shape - Ellipse","hd":false},{"ty":"st","c":{"a":0,"k":[1,1,1,1],"ix":3},"o":{"a":0,"k":100,"ix":4},"w":{"a":0,"k":2,"ix":5},"lc":1,"lj":1,"ml":4,"ml2":{"a":0,"k":4,"ix":8},"bm":0,"nm":"Stroke 1","mn":"ADBE Vector Graphic - Stroke","hd":false},{"ty":"fl","c":{"a":0,"k":[0.890196018593,0.890196018593,0.890196018593,1],"ix":4},"o":{"a":0,"k":100,"ix":5},"r":1,"bm":0,"nm":"Fill 1","mn":"ADBE Vector Graphic - Fill","hd":false},{"ty":"tr","p":{"a":0,"k":[96.516,-1.928],"ix":2},"a":{"a":0,"k":[0,0],"ix":1},"s":{"a":0,"k":[100,100],"ix":3},"r":{"a":0,"k":0,"ix":6},"o":{"a":0,"k":100,"ix":7},"sk":{"a":0,"k":0,"ix":4},"sa":{"a":0,"k":0,"ix":5},"nm":"Transform"}],"nm":"Ellipse 1","np":3,"cix":2,"bm":0,"ix":1,"mn":"ADBE Vector Group","hd":false}],"ip":0,"op":750.000030548126,"st":0,"bm":0},{"ddd":0,"ind":17,"ty":4,"nm":"LockHead Outlines 22","parent":23,"tt":1,"sr":1,"ks":{"o":{"a":0,"k":100,"ix":11},"r":{"a":0,"k":0,"ix":10},"p":{"s":true,"x":{"a":0,"k":136.119,"ix":3},"y":{"a":0,"k":46.519,"ix":4}},"a":{"a":0,"k":[74.757,51.728,0],"ix":1},"s":{"a":0,"k":[73.532,73.532,100],"ix":6}},"ao":0,"shapes":[{"ty":"gr","it":[{"ind":0,"ty":"sh","ix":1,"ks":{"a":0,"k":{"i":[[0,-2.69],[2.69,0],[0,2.69],[-2.691,0]],"o":[[0,2.69],[-2.691,0],[0,-2.69],[2.69,0]],"v":[[4.872,0],[0.001,4.872],[-4.872,0],[0.001,-4.872]],"c":true},"ix":2},"nm":"Path 1","mn":"ADBE Vector Shape - Group","hd":false},{"ty":"fl","c":{"a":0,"k":[0.937254965305,0.078431375325,0.078431375325,1],"ix":4},"o":{"a":1,"k":[{"i":{"x":[0],"y":[1]},"o":{"x":[0.167],"y":[0.167]},"n":["0_1_0p167_0p167"],"t":103.061,"s":[0],"e":[100]},{"i":{"x":[0.833],"y":[0.833]},"o":{"x":[0.758],"y":[0]},"n":["0p833_0p833_0p758_0"],"t":109.061,"s":[100],"e":[0]},{"t":117.061254768002}],"ix":5},"r":1,"bm":0,"nm":"Fill 1","mn":"ADBE Vector Graphic - Fill","hd":false},{"ty":"tr","p":{"a":0,"k":[74.757,51.728],"ix":2},"a":{"a":0,"k":[0,0],"ix":1},"s":{"a":0,"k":[100,100],"ix":3},"r":{"a":0,"k":0,"ix":6},"o":{"a":0,"k":100,"ix":7},"sk":{"a":0,"k":0,"ix":4},"sa":{"a":0,"k":0,"ix":5},"nm":"Transform"}],"nm":"Group 3","np":2,"cix":2,"bm":0,"ix":1,"mn":"ADBE Vector Group","hd":false}],"ip":103.000004195276,"op":120.0000048877,"st":52.0000021180034,"bm":0},{"ddd":0,"ind":18,"ty":4,"nm":"Shape Layer 16","sr":1,"ks":{"o":{"a":0,"k":100,"ix":11},"r":{"a":0,"k":0,"ix":10},"p":{"a":0,"k":[500,500,0],"ix":2},"a":{"a":0,"k":[0,0,0],"ix":1},"s":{"a":0,"k":[100,100,100],"ix":6}},"ao":0,"shapes":[{"ty":"gr","it":[{"d":1,"ty":"el","s":{"a":0,"k":[123.684,123.684],"ix":2},"p":{"a":0,"k":[0,0],"ix":3},"nm":"Ellipse Path 1","mn":"ADBE Vector Shape - Ellipse","hd":false},{"ty":"fl","c":{"a":0,"k":[0.996078431606,0.658823549747,0.658823549747,1],"ix":4},"o":{"a":1,"k":[{"i":{"x":[0.154],"y":[1]},"o":{"x":[0.478],"y":[0]},"n":["0p154_1_0p478_0"],"t":103,"s":[0],"e":[100]},{"i":{"x":[0.561],"y":[1]},"o":{"x":[0.92],"y":[0]},"n":["0p561_1_0p92_0"],"t":107,"s":[100],"e":[0]},{"t":117.000004765508}],"ix":5},"r":1,"bm":0,"nm":"Fill 1","mn":"ADBE Vector Graphic - Fill","hd":false},{"ty":"tr","p":{"a":0,"k":[96.516,-1.928],"ix":2},"a":{"a":0,"k":[0,0],"ix":1},"s":{"a":0,"k":[100,100],"ix":3},"r":{"a":0,"k":0,"ix":6},"o":{"a":0,"k":100,"ix":7},"sk":{"a":0,"k":0,"ix":4},"sa":{"a":0,"k":0,"ix":5},"nm":"Transform"}],"nm":"Ellipse 1","np":2,"cix":2,"bm":0,"ix":1,"mn":"ADBE Vector Group","hd":false}],"ip":103.000004195276,"op":120.0000048877,"st":0,"bm":0},{"ddd":0,"ind":19,"ty":4,"nm":"Bird Wordmark_white Outlines","parent":23,"sr":1,"ks":{"o":{"a":0,"k":100,"ix":11},"r":{"a":0,"k":90,"ix":10},"p":{"a":0,"k":[33.74,58.228,0],"ix":2},"a":{"a":0,"k":[425.5,146.5,0],"ix":1},"s":{"a":0,"k":[6.143,6.143,100],"ix":6}},"ao":0,"shapes":[{"ty":"gr","it":[{"ind":0,"ty":"sh","ix":1,"ks":{"a":0,"k":{"i":[[0,0],[18,0],[0,0],[0,0],[0,0],[0,-18]],"o":[[0,18.1],[0,0],[0,0],[0,0],[18.1,0],[0,0]],"v":[[272.85,-1.4],[240.15,31.3],[219.05,31.3],[219.05,-37.7],[240.15,-37.7],[272.85,-5]],"c":true},"ix":2},"nm":"Path 1","mn":"ADBE Vector Shape - Group","hd":false},{"ind":1,"ty":"sh","ix":2,"ks":{"a":0,"k":{"i":[[31.6,0],[0,0],[0,0],[0,0],[0,36.9]],"o":[[0,0],[0,0],[0,0],[31.6,0],[0,-36.9]],"v":[[238.05,-60.4],[193.85,-60.4],[193.85,54],[238.05,54],[299.25,-3.2]],"c":true},"ix":2},"nm":"Path 2","mn":"ADBE Vector Shape - Group","hd":false},{"ind":2,"ty":"sh","ix":3,"ks":{"a":0,"k":{"i":[[9.1,0],[0,0],[0,0],[0,0],[0,-14.3]],"o":[[0,0],[0,0],[0,0],[9.1,0],[0,14.3]],"v":[[66.55,-4.6],[42.25,-4.6],[42.25,-37.6],[66.55,-37.6],[87.05,-21.1]],"c":true},"ix":2},"nm":"Path 3","mn":"ADBE Vector Shape - Group","hd":false},{"ind":3,"ty":"sh","ix":4,"ks":{"a":0,"k":{"i":[[0,24.3],[26.3,0],[0,0],[0,0],[0,0],[0,0],[0,0],[0,0],[-11.5,6.3],[0,0]],"o":[[0,-24.8],[0,0],[0,0],[0,0],[0,0],[0,0],[0,0],[7.799,11.2],[0,0],[7.3,-2.7]],"v":[[112.55,-22.3],[69.35,-60.4],[17.05,-60.4],[17.05,54],[42.25,54],[42.25,17.4],[62.05,17.4],[80.451,47],[114.85,54.1],[88.05,13.2]],"c":true},"ix":2},"nm":"Path 4","mn":"ADBE Vector Shape - Group","hd":false},{"ind":4,"ty":"sh","ix":5,"ks":{"a":0,"k":{"i":[[0,0],[0,0],[0,0],[0,0]],"o":[[0,0],[0,0],[0,0],[0,0]],"v":[[-96.45,-60.4],[-71.25,-60.4],[-71.25,54],[-96.45,54]],"c":true},"ix":2},"nm":"Path 5","mn":"ADBE Vector Shape - Group","hd":false},{"ind":5,"ty":"sh","ix":6,"ks":{"a":0,"k":{"i":[[7.7,0],[0,0],[0,0],[0,0],[0,-13.3]],"o":[[0,0],[0,0],[0,0],[7.7,0],[-0.1,13.3]],"v":[[-228.95,32],[-253.75,32],[-253.75,6.8],[-228.95,6.8],[-205.95,19.4]],"c":true},"ix":2},"nm":"Path 6","mn":"ADBE Vector Shape - Group","hd":false},{"ind":6,"ty":"sh","ix":7,"ks":{"a":0,"k":{"i":[[0,0],[0,0],[0,-12.1],[6.7,0],[0,0]],"o":[[0,0],[6.7,0],[0,12.1],[0,0],[0,0]],"v":[[-253.75,-38.3],[-232.25,-38.3],[-212.35,-26.2],[-232.25,-14.1],[-253.75,-14.1]],"c":true},"ix":2},"nm":"Path 7","mn":"ADBE Vector Shape - Group","hd":false},{"ind":7,"ty":"sh","ix":8,"ks":{"a":0,"k":{"i":[[13.7,5.6],[0,9.9],[0,0],[20.5,0],[0,0],[-12.2,-0.8],[0,0],[0,0],[0,16.9]],"o":[[10.2,-6.1],[0,0],[0,-19.8],[0,0],[0.7,11.3],[0,0],[0,0],[31.3,0],[0,-15.9]],"v":[[-202.45,-5.8],[-187.55,-29.3],[-187.55,-30.5],[-224.55,-60.4],[-299.25,-60.4],[-278.25,-38.6],[-278.25,54.1],[-223.95,54.1],[-181.15,22.7]],"c":true},"ix":2},"nm":"Path 8","mn":"ADBE Vector Shape - Group","hd":false},{"ty":"mm","mm":1,"nm":"Merge Paths 1","mn":"ADBE Vector Filter - Merge","hd":false},{"ty":"fl","c":{"a":0,"k":[1,1,1,1],"ix":4},"o":{"a":0,"k":100,"ix":5},"r":1,"bm":0,"nm":"Fill 1","mn":"ADBE Vector Graphic - Fill","hd":false},{"ty":"tr","p":{"a":0,"k":[417.45,144.8],"ix":2},"a":{"a":0,"k":[0,0],"ix":1},"s":{"a":0,"k":[100,100],"ix":3},"r":{"a":0,"k":0,"ix":6},"o":{"a":0,"k":100,"ix":7},"sk":{"a":0,"k":0,"ix":4},"sa":{"a":0,"k":0,"ix":5},"nm":"Transform"}],"nm":"Group 1","np":10,"cix":2,"bm":0,"ix":1,"mn":"ADBE Vector Group","hd":false}],"ip":0,"op":408.000016618181,"st":0,"bm":0},{"ddd":0,"ind":22,"ty":4,"nm":"Lock Outlines 2","parent":23,"sr":1,"ks":{"o":{"a":0,"k":100,"ix":11},"r":{"a":0,"k":0,"ix":10},"p":{"s":true,"x":{"a":0,"k":112.5,"ix":3},"y":{"a":0,"k":57.5,"ix":4}},"a":{"a":0,"k":[112.5,57.5,0],"ix":1},"s":{"a":0,"k":[100,100,100],"ix":6}},"ao":0,"shapes":[{"ty":"gr","it":[{"ind":0,"ty":"sh","ix":1,"ks":{"a":0,"k":{"i":[[0,0],[-3.095,0],[5.704,0]],"o":[[0,0],[5.158,0],[-4.308,0]],"v":[[136.347,60.716],[141.565,60.777],[141.019,52.585]],"c":false},"ix":2},"nm":"Path 1","mn":"ADBE Vector Shape - Group","hd":false},{"ty":"st","c":{"a":0,"k":[0.168627455831,0.168627455831,0.168627455831,1],"ix":3},"o":{"a":0,"k":100,"ix":4},"w":{"a":0,"k":2,"ix":5},"lc":1,"lj":1,"ml":4,"ml2":{"a":0,"k":4,"ix":8},"bm":0,"nm":"Stroke 1","mn":"ADBE Vector Graphic - Stroke","hd":false},{"ty":"tr","p":{"a":0,"k":[-2,0],"ix":2},"a":{"a":0,"k":[0,0],"ix":1},"s":{"a":0,"k":[100,100],"ix":3},"r":{"a":0,"k":0,"ix":6},"o":{"a":0,"k":100,"ix":7},"sk":{"a":0,"k":0,"ix":4},"sa":{"a":0,"k":0,"ix":5},"nm":"Transform"}],"nm":"Shape 1","np":2,"cix":2,"bm":0,"ix":1,"mn":"ADBE Vector Group","hd":false},{"ty":"gr","it":[{"ind":0,"ty":"sh","ix":1,"ks":{"a":0,"k":{"i":[[0,0],[0,0],[1.163,0],[0,0],[0,-1.163],[0,0],[-1.164,0],[0,0],[0,1.163],[0,0]],"o":[[0,0],[0,-1.163],[0,0],[-1.164,0],[0,0],[0,1.163],[0,0],[1.163,0],[0,0],[0,0]],"v":[[1.977,0.279],[1.977,-5.326],[-0.13,-7.432],[-4.897,-7.432],[-7.004,-5.326],[-7.004,1.769],[-4.897,3.875],[-0.13,3.875],[1.977,1.769],[1.977,1.286]],"c":true},"ix":2},"nm":"Path 2","mn":"ADBE Vector Shape - Group","hd":false},{"ty":"mm","mm":1,"nm":"Merge Paths 1","mn":"ADBE Vector Filter - Merge","hd":false},{"ty":"fl","c":{"a":0,"k":[0.169000004787,0.169000004787,0.169000004787,1],"ix":4},"o":{"a":0,"k":100,"ix":5},"r":1,"bm":0,"nm":"Fill 1","mn":"ADBE Vector Graphic - Fill","hd":false},{"ty":"tr","p":{"a":0,"k":[134.57,58.975],"ix":2},"a":{"a":0,"k":[0,0],"ix":1},"s":{"a":0,"k":[100,100],"ix":3},"r":{"a":0,"k":0,"ix":6},"o":{"a":0,"k":100,"ix":7},"sk":{"a":0,"k":0,"ix":4},"sa":{"a":0,"k":0,"ix":5},"nm":"Transform"}],"nm":"Group 2","np":3,"cix":2,"bm":0,"ix":2,"mn":"ADBE Vector Group","hd":false},{"ty":"gr","it":[{"ind":0,"ty":"sh","ix":1,"ks":{"a":0,"k":{"i":[[8.34,0],[0,-8.34],[-8.34,0],[0,8.341]],"o":[[-8.34,0],[0,8.341],[8.34,0],[0,-8.34]],"v":[[-0.001,-15.126],[-15.125,0.002],[-0.001,15.126],[15.124,0.002]],"c":true},"ix":2},"nm":"Path 2","mn":"ADBE Vector Shape - Group","hd":false},{"ty":"mm","mm":1,"nm":"Merge Paths 1","mn":"ADBE Vector Filter - Merge","hd":false},{"ty":"fl","c":{"a":0,"k":[0.937254965305,0.937254965305,0.937254965305,1],"ix":4},"o":{"a":0,"k":100,"ix":5},"r":1,"bm":0,"nm":"Fill 1","mn":"ADBE Vector Graphic - Fill","hd":false},{"ty":"tr","p":{"a":0,"k":[135.793,57.158],"ix":2},"a":{"a":0,"k":[0,0],"ix":1},"s":{"a":0,"k":[100,100],"ix":3},"r":{"a":0,"k":0,"ix":6},"o":{"a":0,"k":100,"ix":7},"sk":{"a":0,"k":0,"ix":4},"sa":{"a":0,"k":0,"ix":5},"nm":"Transform"}],"nm":"Group 3","np":3,"cix":2,"bm":0,"ix":3,"mn":"ADBE Vector Group","hd":false}],"ip":-3.00000012219251,"op":398.000016210872,"st":38.0000015477717,"bm":0},{"ddd":0,"ind":23,"ty":4,"nm":"Lock Outlines","sr":1,"ks":{"o":{"a":0,"k":100,"ix":11},"r":{"a":0,"k":0,"ix":10},"p":{"s":true,"x":{"a":1,"k":[{"i":{"x":[0.372],"y":[1]},"o":{"x":[0.716],"y":[0]},"n":["0p372_1_0p716_0"],"t":230,"s":[500],"e":[761]},{"i":{"x":[0.372],"y":[1]},"o":{"x":[0],"y":[0]},"n":["0p372_1_0_0"],"t":258,"s":[761],"e":[761]},{"i":{"x":[0.548],"y":[1]},"o":{"x":[0.619],"y":[0]},"n":["0p548_1_0p619_0"],"t":326,"s":[761],"e":[500]},{"t":355.352514473804}],"ix":3},"y":{"a":1,"k":[{"i":{"x":[0.496],"y":[1]},"o":{"x":[0.558],"y":[0]},"n":["0p496_1_0p558_0"],"t":0,"s":[-519],"e":[500]},{"i":{"x":[0.833],"y":[1]},"o":{"x":[0.167],"y":[0]},"n":["0p833_1_0p167_0"],"t":28,"s":[500],"e":[500]},{"i":{"x":[0.372],"y":[1]},"o":{"x":[0.734],"y":[0]},"n":["0p372_1_0p734_0"],"t":230,"s":[500],"e":[302]},{"i":{"x":[0.372],"y":[1]},"o":{"x":[0],"y":[0]},"n":["0p372_1_0_0"],"t":258,"s":[302],"e":[302]},{"i":{"x":[0.549],"y":[1]},"o":{"x":[0.649],"y":[0]},"n":["0p549_1_0p649_0"],"t":326,"s":[302],"e":[1141]},{"t":365.000014866755}],"ix":4}},"a":{"a":0,"k":[112.5,57.5,0],"ix":1},"s":{"a":1,"k":[{"i":{"x":[0.399,0.399,1],"y":[1,1,1]},"o":{"x":[0.717,0.717,0],"y":[0,0,0]},"n":["0p399_1_0p717_0","0p399_1_0p717_0","1_1_0_0"],"t":20.073,"s":[278.01,278.01,100],"e":[412.01,412.01,100]},{"i":{"x":[0.399,0.399,1],"y":[1,1,1]},"o":{"x":[0.167,0.167,0.167],"y":[0,0,0]},"n":["0p399_1_0p167_0","0p399_1_0p167_0","1_1_0p167_0"],"t":43.073,"s":[412.01,412.01,100],"e":[412.01,412.01,100]},{"i":{"x":[0.485,0.485,0.833],"y":[1,1,1]},"o":{"x":[0.671,0.671,0.167],"y":[0,0,0]},"n":["0p485_1_0p671_0","0p485_1_0p671_0","0p833_1_0p167_0"],"t":230,"s":[412.01,412.01,100],"e":[519.01,519.01,100]},{"i":{"x":[0.399,0.399,1],"y":[1,1,1]},"o":{"x":[0,0,0],"y":[0,0,0]},"n":["0p399_1_0_0","0p399_1_0_0","1_1_0_0"],"t":258,"s":[519.01,519.01,100],"e":[519.01,519.01,100]},{"i":{"x":[0.559,0.559,0.833],"y":[1,1,1]},"o":{"x":[0.58,0.58,0.167],"y":[0,0,0]},"n":["0p559_1_0p58_0","0p559_1_0p58_0","0p833_1_0p167_0"],"t":326,"s":[519.01,519.01,100],"e":[278.01,278.01,100]},{"t":355.352514473804}],"ix":6}},"ao":0,"shapes":[{"ty":"gr","it":[{"ind":0,"ty":"sh","ix":1,"ks":{"a":0,"k":{"i":[[0,0],[-3.095,0],[5.704,0]],"o":[[0,0],[5.158,0],[-4.308,0]],"v":[[136.347,60.716],[141.565,60.777],[141.019,52.585]],"c":false},"ix":2},"nm":"Path 1","mn":"ADBE Vector Shape - Group","hd":false},{"ty":"st","c":{"a":0,"k":[0.168627455831,0.168627455831,0.168627455831,1],"ix":3},"o":{"a":0,"k":100,"ix":4},"w":{"a":0,"k":2,"ix":5},"lc":1,"lj":1,"ml":4,"ml2":{"a":0,"k":4,"ix":8},"bm":0,"nm":"Stroke 1","mn":"ADBE Vector Graphic - Stroke","hd":false},{"ty":"tr","p":{"a":0,"k":[-2,0],"ix":2},"a":{"a":0,"k":[0,0],"ix":1},"s":{"a":0,"k":[100,100],"ix":3},"r":{"a":0,"k":0,"ix":6},"o":{"a":0,"k":100,"ix":7},"sk":{"a":0,"k":0,"ix":4},"sa":{"a":0,"k":0,"ix":5},"nm":"Transform"}],"nm":"Shape 1","np":2,"cix":2,"bm":0,"ix":1,"mn":"ADBE Vector Group","hd":false},{"ty":"gr","it":[{"ind":0,"ty":"sh","ix":1,"ks":{"a":0,"k":{"i":[[0,0],[0,0],[1.163,0],[0,0],[0,-1.163],[0,0],[-1.164,0],[0,0],[0,1.163],[0,0]],"o":[[0,0],[0,-1.163],[0,0],[-1.164,0],[0,0],[0,1.163],[0,0],[1.163,0],[0,0],[0,0]],"v":[[1.977,0.279],[1.977,-5.326],[-0.13,-7.432],[-4.897,-7.432],[-7.004,-5.326],[-7.004,1.769],[-4.897,3.875],[-0.13,3.875],[1.977,1.769],[1.977,1.286]],"c":true},"ix":2},"nm":"Path 2","mn":"ADBE Vector Shape - Group","hd":false},{"ty":"mm","mm":1,"nm":"Merge Paths 1","mn":"ADBE Vector Filter - Merge","hd":false},{"ty":"fl","c":{"a":0,"k":[0.169000004787,0.169000004787,0.169000004787,1],"ix":4},"o":{"a":0,"k":100,"ix":5},"r":1,"bm":0,"nm":"Fill 1","mn":"ADBE Vector Graphic - Fill","hd":false},{"ty":"tr","p":{"a":0,"k":[134.57,58.975],"ix":2},"a":{"a":0,"k":[0,0],"ix":1},"s":{"a":0,"k":[100,100],"ix":3},"r":{"a":0,"k":0,"ix":6},"o":{"a":0,"k":100,"ix":7},"sk":{"a":0,"k":0,"ix":4},"sa":{"a":0,"k":0,"ix":5},"nm":"Transform"}],"nm":"Group 2","np":3,"cix":2,"bm":0,"ix":2,"mn":"ADBE Vector Group","hd":false},{"ty":"gr","it":[{"ind":0,"ty":"sh","ix":1,"ks":{"a":0,"k":{"i":[[8.34,0],[0,-8.34],[-8.34,0],[0,8.341]],"o":[[-8.34,0],[0,8.341],[8.34,0],[0,-8.34]],"v":[[-0.001,-15.126],[-15.125,0.002],[-0.001,15.126],[15.124,0.002]],"c":true},"ix":2},"nm":"Path 2","mn":"ADBE Vector Shape - Group","hd":false},{"ty":"mm","mm":1,"nm":"Merge Paths 1","mn":"ADBE Vector Filter - Merge","hd":false},{"ty":"fl","c":{"a":0,"k":[0.937254965305,0.937254965305,0.937254965305,1],"ix":4},"o":{"a":0,"k":100,"ix":5},"r":1,"bm":0,"nm":"Fill 1","mn":"ADBE Vector Graphic - Fill","hd":false},{"ty":"tr","p":{"a":0,"k":[135.793,57.158],"ix":2},"a":{"a":0,"k":[0,0],"ix":1},"s":{"a":0,"k":[100,100],"ix":3},"r":{"a":0,"k":0,"ix":6},"o":{"a":0,"k":100,"ix":7},"sk":{"a":0,"k":0,"ix":4},"sa":{"a":0,"k":0,"ix":5},"nm":"Transform"}],"nm":"Group 3","np":3,"cix":2,"bm":0,"ix":3,"mn":"ADBE Vector Group","hd":false},{"ty":"gr","it":[{"ind":0,"ty":"sh","ix":1,"ks":{"a":0,"k":{"i":[[-0.883,0],[0,0],[0,-0.882],[0,0],[0.882,0],[0,0],[0,0.883],[0,0]],"o":[[0,0],[0.882,0],[0,0],[0,0.883],[0,0],[-0.883,0],[0,0],[0,-0.882]],"v":[[-2.383,-5.151],[2.383,-5.151],[3.988,-3.547],[3.988,3.545],[2.383,5.151],[-2.383,5.151],[-3.988,3.545],[-3.988,-3.547]],"c":true},"ix":2},"nm":"Path 1","mn":"ADBE Vector Shape - Group","hd":false},{"ty":"fl","c":{"a":0,"k":[0.258999992819,0.258999992819,0.258999992819,1],"ix":4},"o":{"a":0,"k":100,"ix":5},"r":1,"bm":0,"nm":"Fill 1","mn":"ADBE Vector Graphic - Fill","hd":false},{"ty":"tr","p":{"a":0,"k":[133.719,55.165],"ix":2},"a":{"a":0,"k":[0,0],"ix":1},"s":{"a":0,"k":[100,100],"ix":3},"r":{"a":0,"k":0,"ix":6},"o":{"a":0,"k":100,"ix":7},"sk":{"a":0,"k":0,"ix":4},"sa":{"a":0,"k":0,"ix":5},"nm":"Transform"}],"nm":"Group 4","np":2,"cix":2,"bm":0,"ix":4,"mn":"ADBE Vector Group","hd":false},{"ty":"gr","it":[{"ind":0,"ty":"sh","ix":1,"ks":{"a":0,"k":{"i":[[0,-8.076],[8.076,0],[0,8.075],[-8.075,0]],"o":[[0,8.075],[-8.075,0],[0,-8.076],[8.076,0]],"v":[[14.622,0.001],[0,14.622],[-14.622,0.001],[0,-14.622]],"c":true},"ix":2},"nm":"Path 1","mn":"ADBE Vector Shape - Group","hd":false},{"ty":"fl","c":{"a":0,"k":[0.258999992819,0.258999992819,0.258999992819,1],"ix":4},"o":{"a":0,"k":100,"ix":5},"r":1,"bm":0,"nm":"Fill 1","mn":"ADBE Vector Graphic - Fill","hd":false},{"ty":"tr","p":{"a":0,"k":[135.792,57.158],"ix":2},"a":{"a":0,"k":[0,0],"ix":1},"s":{"a":0,"k":[100,100],"ix":3},"r":{"a":0,"k":0,"ix":6},"o":{"a":0,"k":100,"ix":7},"sk":{"a":0,"k":0,"ix":4},"sa":{"a":0,"k":0,"ix":5},"nm":"Transform"}],"nm":"Group 5","np":2,"cix":2,"bm":0,"ix":5,"mn":"ADBE Vector Group","hd":false},{"ty":"gr","it":[{"ind":0,"ty":"sh","ix":1,"ks":{"a":0,"k":{"i":[[0,0],[-19.729,0],[0,0],[19.729,0]],"o":[[-19.729,0],[0,0],[19.729,0],[0,0]],"v":[[-51.688,33.801],[-51.688,-33.801],[51.688,-33.801],[51.688,33.801]],"c":true},"ix":2},"nm":"Path 1","mn":"ADBE Vector Shape - Group","hd":false},{"ty":"st","c":{"a":0,"k":[0,0,0,1],"ix":3},"o":{"a":0,"k":100,"ix":4},"w":{"a":0,"k":2,"ix":5},"lc":1,"lj":1,"ml":4,"ml2":{"a":0,"k":4,"ix":8},"bm":0,"nm":"Stroke 1","mn":"ADBE Vector Graphic - Stroke","hd":false},{"ty":"fl","c":{"a":0,"k":[0.109803922474,0.109803922474,0.109803922474,1],"ix":4},"o":{"a":0,"k":100,"ix":5},"r":1,"bm":0,"nm":"Fill 1","mn":"ADBE Vector Graphic - Fill","hd":false},{"ty":"tr","p":{"a":0,"k":[112.426,57.158],"ix":2},"a":{"a":0,"k":[0,0],"ix":1},"s":{"a":0,"k":[100,100],"ix":3},"r":{"a":0,"k":0,"ix":6},"o":{"a":0,"k":100,"ix":7},"sk":{"a":0,"k":0,"ix":4},"sa":{"a":0,"k":0,"ix":5},"nm":"Transform"}],"nm":"Group 7","np":3,"cix":2,"bm":0,"ix":6,"mn":"ADBE Vector Group","hd":false},{"ty":"gr","it":[{"ind":0,"ty":"sh","ix":1,"ks":{"a":0,"k":{"i":[[0,0],[-33.361,0],[0,0],[33.36,0]],"o":[[-33.361,0],[0,0],[33.36,0],[0,0]],"v":[[-87.405,57.158],[-87.405,-57.158],[87.406,-57.158],[87.406,57.158]],"c":true},"ix":2},"nm":"Path 1","mn":"ADBE Vector Shape - Group","hd":false},{"ty":"fl","c":{"a":0,"k":[0.109803922474,0.109803922474,0.109803922474,1],"ix":4},"o":{"a":0,"k":100,"ix":5},"r":1,"bm":0,"nm":"Fill 1","mn":"ADBE Vector Graphic - Fill","hd":false},{"ty":"tr","p":{"a":0,"k":[112.426,57.158],"ix":2},"a":{"a":0,"k":[0,0],"ix":1},"s":{"a":0,"k":[83.903,83.903],"ix":3},"r":{"a":0,"k":0,"ix":6},"o":{"a":0,"k":100,"ix":7},"sk":{"a":0,"k":0,"ix":4},"sa":{"a":0,"k":0,"ix":5},"nm":"Transform"}],"nm":"Group 8","np":4,"cix":2,"bm":0,"ix":7,"mn":"ADBE Vector Group","hd":false}],"ip":-3.00000012219251,"op":398.000016210872,"st":38.0000015477717,"bm":0},{"ddd":0,"ind":24,"ty":4,"nm":"Cable Outlines","parent":23,"sr":1,"ks":{"o":{"a":0,"k":100,"ix":11},"r":{"a":0,"k":0,"ix":10},"p":{"a":0,"k":[233.856,131.285,0],"ix":2},"a":{"a":0,"k":[93.5,138,0],"ix":1},"s":{"a":0,"k":[64.004,64.004,100],"ix":6}},"ao":0,"shapes":[{"ty":"gr","it":[{"ind":0,"ty":"sh","ix":1,"ks":{"a":0,"k":{"i":[[0,-0.778],[0.778,0],[0,0],[0,0.778],[-0.778,0],[0,0]],"o":[[0,0.778],[0,0],[-0.778,0],[0,-0.778],[0,0],[0.778,0]],"v":[[6.725,0],[5.318,1.407],[-5.318,1.407],[-6.725,0],[-5.318,-1.407],[5.318,-1.407]],"c":true},"ix":2},"nm":"Path 1","mn":"ADBE Vector Shape - Group","hd":false},{"ty":"fl","c":{"a":0,"k":[0.847000002394,0.847000002394,0.847000002394,1],"ix":4},"o":{"a":0,"k":100,"ix":5},"r":1,"bm":0,"nm":"Fill 1","mn":"ADBE Vector Graphic - Fill","hd":false},{"ty":"tr","p":{"a":0,"k":[37.307,22.604],"ix":2},"a":{"a":0,"k":[0,0],"ix":1},"s":{"a":0,"k":[100,100],"ix":3},"r":{"a":0,"k":0,"ix":6},"o":{"a":0,"k":100,"ix":7},"sk":{"a":0,"k":0,"ix":4},"sa":{"a":0,"k":0,"ix":5},"nm":"Transform"}],"nm":"Group 1","np":2,"cix":2,"bm":0,"ix":1,"mn":"ADBE Vector Group","hd":false},{"ty":"gr","it":[{"ind":0,"ty":"sh","ix":1,"ks":{"a":0,"k":{"i":[[0,-0.778],[0,0],[0.778,0.004],[3.898,-2.681],[0.44,0.641],[-0.641,0.436],[-8.827,-0.02]],"o":[[0,0],[0,0.778],[-8.234,-0.016],[-0.641,0.44],[-0.44,-0.644],[4.386,-3.019],[0.774,0]],"v":[[10.919,-2.191],[10.919,-2.187],[9.507,-0.784],[-8.52,3.178],[-10.479,2.816],[-10.117,0.859],[9.516,-3.598]],"c":true},"ix":2},"nm":"Path 1","mn":"ADBE Vector Shape - Group","hd":false},{"ty":"fl","c":{"a":0,"k":[0.847000002394,0.847000002394,0.847000002394,1],"ix":4},"o":{"a":0,"k":100,"ix":5},"r":1,"bm":0,"nm":"Fill 1","mn":"ADBE Vector Graphic - Fill","hd":false},{"ty":"tr","p":{"a":0,"k":[13.284,17.595],"ix":2},"a":{"a":0,"k":[0,0],"ix":1},"s":{"a":0,"k":[100,100],"ix":3},"r":{"a":0,"k":0,"ix":6},"o":{"a":0,"k":100,"ix":7},"sk":{"a":0,"k":0,"ix":4},"sa":{"a":0,"k":0,"ix":5},"nm":"Transform"}],"nm":"Group 2","np":2,"cix":2,"bm":0,"ix":2,"mn":"ADBE Vector Group","hd":false},{"ty":"gr","it":[{"ind":0,"ty":"sh","ix":1,"ks":{"a":0,"k":{"i":[[50.39,6.256],[0,0],[2.913,0],[22.792,0.222],[0,-3.174],[0,0],[0,0],[0,0],[-2.644,0],[-14.088,2.896],[0,3.497],[0,0],[0,-48.416],[9.964,-19.42],[16.149,0],[0,0],[0,0],[0,0],[-14.617,28.495],[0,33.117]],"o":[[0,0],[0,-3.498],[-14.088,-2.897],[-2.644,0],[0,0],[0,0],[0,0],[0,3.175],[22.792,-0.221],[2.913,0],[0,0],[31.084,7.253],[0,28.621],[-10.195,19.88],[0,0],[0,0],[0,0],[25.999,0],[11.964,-23.328],[0,-60.295]],"v":[[-2.958,-124.988],[-2.958,-127.519],[-8.256,-133.878],[-65.697,-137.903],[-70.505,-132.132],[-70.505,-114.769],[-70.505,-107.362],[-70.505,-89.999],[-65.697,-84.228],[-8.256,-88.252],[-2.958,-94.611],[-2.958,-98.411],[44.344,6.187],[28.669,81.78],[-11.035,111.741],[-54.897,111.741],[-54.897,137.902],[-11.035,137.902],[51.949,93.717],[70.505,6.187]],"c":true},"ix":2},"nm":"Path 1","mn":"ADBE Vector Shape - Group","hd":false},{"ty":"fl","c":{"a":0,"k":[0.109803922474,0.109803922474,0.109803922474,1],"ix":4},"o":{"a":0,"k":100,"ix":5},"r":1,"bm":0,"nm":"Fill 1","mn":"ADBE Vector Graphic - Fill","hd":false},{"ty":"tr","p":{"a":0,"k":[116.143,137.902],"ix":2},"a":{"a":0,"k":[0,0],"ix":1},"s":{"a":0,"k":[100,100],"ix":3},"r":{"a":0,"k":0,"ix":6},"o":{"a":0,"k":100,"ix":7},"sk":{"a":0,"k":0,"ix":4},"sa":{"a":0,"k":0,"ix":5},"nm":"Transform"}],"nm":"Group 3","np":4,"cix":2,"bm":0,"ix":3,"mn":"ADBE Vector Group","hd":false},{"ty":"gr","it":[{"ind":0,"ty":"sh","ix":1,"ks":{"a":0,"k":{"i":[[1.05,-0.442],[2.086,-1.277],[0,-2.261],[0,0],[-1.868,-1.2],[-2.205,-0.883],[-1.102,0],[0,0],[0,2.69],[0,0],[-1.184,0],[0,0],[-0.961,3.581],[5.198,0],[0,0],[0,1.184],[0,0],[2.689,0],[0,0]],"o":[[-2.152,0.906],[-1.928,1.182],[0,0],[0,2.22],[2.07,1.329],[1.023,0.41],[0,0],[2.689,0],[0,0],[0,-1.184],[0,0],[3.708,0],[1.453,-5.416],[0,0],[-1.184,0],[0,0],[0,-2.689],[0,0],[-1.14,0]],"v":[[-42.767,-15.622],[-49.665,-12.475],[-52.752,-6.926],[-52.752,6.895],[-49.762,12.382],[-42.811,15.665],[-39.604,16.284],[-29.062,16.284],[-24.173,11.393],[-24.173,10.286],[-22.029,8.141],[43.167,8.141],[51.299,2.212],[43.453,-8.143],[-22.029,-8.143],[-24.173,-10.285],[-24.173,-11.393],[-29.062,-16.284],[-39.458,-16.284]],"c":true},"ix":2},"nm":"Path 1","mn":"ADBE Vector Shape - Group","hd":false},{"ty":"fl","c":{"a":0,"k":[0.647000002394,0.647000002394,0.647000002394,1],"ix":4},"o":{"a":0,"k":100,"ix":5},"r":1,"bm":0,"nm":"Fill 1","mn":"ADBE Vector Graphic - Fill","hd":false},{"ty":"tr","p":{"a":0,"k":[52.752,26.918],"ix":2},"a":{"a":0,"k":[0,0],"ix":1},"s":{"a":0,"k":[100,100],"ix":3},"r":{"a":0,"k":0,"ix":6},"o":{"a":0,"k":100,"ix":7},"sk":{"a":0,"k":0,"ix":4},"sa":{"a":0,"k":0,"ix":5},"nm":"Transform"}],"nm":"Group 4","np":2,"cix":2,"bm":0,"ix":4,"mn":"ADBE Vector Group","hd":false}],"ip":-3.00000012219251,"op":398.000016210872,"st":38.0000015477717,"bm":0},{"ddd":0,"ind":26,"ty":4,"nm":"LockHead Outlines 6","parent":28,"sr":1,"ks":{"o":{"a":0,"k":100,"ix":11},"r":{"a":0,"k":0,"ix":10},"p":{"s":true,"x":{"a":1,"k":[{"i":{"x":[0.833],"y":[1]},"o":{"x":[0.027],"y":[0]},"n":["0p833_1_0p027_0"],"t":63,"s":[-90],"e":[-90]},{"i":{"x":[0.973],"y":[1]},"o":{"x":[0.167],"y":[0]},"n":["0p973_1_0p167_0"],"t":74,"s":[-90],"e":[-90]},{"t":85.000003462121}],"ix":3},"y":{"a":1,"k":[{"i":{"x":[0.542],"y":[1]},"o":{"x":[0.423],"y":[0]},"n":["0p542_1_0p423_0"],"t":63,"s":[10],"e":[16.5]},{"i":{"x":[0.471],"y":[1]},"o":{"x":[0.458],"y":[0]},"n":["0p471_1_0p458_0"],"t":74,"s":[16.5],"e":[10]},{"t":85.000003462121}],"ix":4}},"a":{"a":0,"k":[63,52,0],"ix":1},"s":{"a":0,"k":[707.649,707.649,100],"ix":6}},"ao":0,"shapes":[{"ty":"gr","it":[{"ind":0,"ty":"sh","ix":1,"ks":{"a":0,"k":{"i":[[0,-2.69],[2.69,0],[0,2.69],[-2.691,0]],"o":[[0,2.69],[-2.691,0],[0,-2.69],[2.69,0]],"v":[[4.872,0],[0.001,4.872],[-4.872,0],[0.001,-4.872]],"c":true},"ix":2},"nm":"Path 1","mn":"ADBE Vector Shape - Group","hd":false},{"ty":"fl","c":{"a":1,"k":[{"i":{"x":[0.833],"y":[0.833]},"o":{"x":[0.167],"y":[0.167]},"n":["0p833_0p833_0p167_0p167"],"t":69,"s":[0.258823543787,0.258823543787,0.258823543787,1],"e":[0.198529407382,0.198529407382,0.198529407382,1]},{"i":{"x":[0.833],"y":[0.833]},"o":{"x":[0.167],"y":[0.167]},"n":["0p833_0p833_0p167_0p167"],"t":74,"s":[0.198529407382,0.198529407382,0.198529407382,1],"e":[0.258823543787,0.258823543787,0.258823543787,1]},{"t":79.000003217736}],"ix":4},"o":{"a":0,"k":100,"ix":5},"r":1,"bm":0,"nm":"Fill 1","mn":"ADBE Vector Graphic - Fill","hd":false},{"ty":"tr","p":{"a":0,"k":[74.757,51.728],"ix":2},"a":{"a":0,"k":[0,0],"ix":1},"s":{"a":0,"k":[100,100],"ix":3},"r":{"a":0,"k":0,"ix":6},"o":{"a":0,"k":100,"ix":7},"sk":{"a":0,"k":0,"ix":4},"sa":{"a":0,"k":0,"ix":5},"nm":"Transform"}],"nm":"Group 3","np":2,"cix":2,"bm":0,"ix":1,"mn":"ADBE Vector Group","hd":false}],"ip":-3.00000012219251,"op":398.000016210872,"st":38.0000015477717,"bm":0},{"ddd":0,"ind":27,"ty":4,"nm":"LockHead Outlines 7","parent":28,"sr":1,"ks":{"o":{"a":0,"k":100,"ix":11},"r":{"a":0,"k":0,"ix":10},"p":{"a":0,"k":[-90,10,0],"ix":2},"a":{"a":0,"k":[63,52,0],"ix":1},"s":{"a":0,"k":[707.649,707.649,100],"ix":6}},"ao":0,"shapes":[{"ty":"gr","it":[{"ind":0,"ty":"sh","ix":1,"ks":{"a":0,"k":{"i":[[0,-2.69],[2.69,0],[0,2.69],[-2.691,0]],"o":[[0,2.69],[-2.691,0],[0,-2.69],[2.69,0]],"v":[[4.872,0],[0.001,4.872],[-4.872,0],[0.001,-4.872]],"c":true},"ix":2},"nm":"Path 1","mn":"ADBE Vector Shape - Group","hd":false},{"ty":"fl","c":{"a":0,"k":[0.168627455831,0.168627455831,0.168627455831,1],"ix":4},"o":{"a":0,"k":100,"ix":5},"r":1,"bm":0,"nm":"Fill 1","mn":"ADBE Vector Graphic - Fill","hd":false},{"ty":"tr","p":{"a":0,"k":[74.757,51.728],"ix":2},"a":{"a":0,"k":[0,0],"ix":1},"s":{"a":0,"k":[100,100],"ix":3},"r":{"a":0,"k":0,"ix":6},"o":{"a":0,"k":100,"ix":7},"sk":{"a":0,"k":0,"ix":4},"sa":{"a":0,"k":0,"ix":5},"nm":"Transform"}],"nm":"Group 3","np":2,"cix":2,"bm":0,"ix":1,"mn":"ADBE Vector Group","hd":false}],"ip":-3.00000012219251,"op":398.000016210872,"st":38.0000015477717,"bm":0},{"ddd":0,"ind":28,"ty":4,"nm":"Shape Layer 1","parent":23,"sr":1,"ks":{"o":{"a":0,"k":100,"ix":11},"r":{"a":0,"k":0,"ix":10},"p":{"a":0,"k":[156.665,52.404,0],"ix":2},"a":{"a":0,"k":[0,0,0],"ix":1},"s":{"a":0,"k":[48.532,48.532,100],"ix":6}},"ao":0,"shapes":[{"ty":"gr","it":[{"d":1,"ty":"el","s":{"a":1,"k":[{"i":{"x":[0.464,0.464],"y":[1,1]},"o":{"x":[0.633,0.633],"y":[0,0]},"n":["0p464_1_0p633_0","0p464_1_0p633_0"],"t":67,"s":[64.424,64.424],"e":[151.424,151.424]},{"t":83.0000033806593}],"ix":2},"p":{"a":0,"k":[0,0],"ix":3},"nm":"Ellipse Path 1","mn":"ADBE Vector Shape - Ellipse","hd":false},{"ty":"st","c":{"a":1,"k":[{"i":{"x":[0.833],"y":[0.833]},"o":{"x":[0.167],"y":[0.167]},"n":["0p833_0p833_0p167_0p167"],"t":67,"s":[1,1,1,1],"e":[1,1,1,1]},{"i":{"x":[0.833],"y":[0.833]},"o":{"x":[0.167],"y":[0.167]},"n":["0p833_0p833_0p167_0p167"],"t":75,"s":[1,1,1,1],"e":[1,1,1,1]},{"t":83.0000033806593}],"ix":3},"o":{"a":1,"k":[{"i":{"x":[0.833],"y":[0.833]},"o":{"x":[0.167],"y":[0.167]},"n":["0p833_0p833_0p167_0p167"],"t":67,"s":[100],"e":[100]},{"i":{"x":[0.833],"y":[0.833]},"o":{"x":[0.167],"y":[0.167]},"n":["0p833_0p833_0p167_0p167"],"t":75,"s":[100],"e":[0]},{"t":83.0000033806593}],"ix":4},"w":{"a":1,"k":[{"i":{"x":[0.833],"y":[0.833]},"o":{"x":[0.167],"y":[0.167]},"n":["0p833_0p833_0p167_0p167"],"t":67,"s":[0],"e":[8]},{"t":68.0000027696968}],"ix":5},"lc":1,"lj":1,"ml":4,"ml2":{"a":0,"k":4,"ix":8},"bm":0,"nm":"Stroke 1","mn":"ADBE Vector Graphic - Stroke","hd":false},{"ty":"fl","c":{"a":0,"k":[0.890196018593,0.890196018593,0.890196018593,1],"ix":4},"o":{"a":0,"k":0,"ix":5},"r":1,"bm":0,"nm":"Fill 1","mn":"ADBE Vector Graphic - Fill","hd":false},{"ty":"tr","p":{"a":0,"k":[-6.788,11.212],"ix":2},"a":{"a":0,"k":[0,0],"ix":1},"s":{"a":0,"k":[100,100],"ix":3},"r":{"a":0,"k":0,"ix":6},"o":{"a":0,"k":100,"ix":7},"sk":{"a":0,"k":0,"ix":4},"sa":{"a":0,"k":0,"ix":5},"nm":"Transform"}],"nm":"Ellipse 1","np":3,"cix":2,"bm":0,"ix":1,"mn":"ADBE Vector Group","hd":false}],"ip":47.0000019143492,"op":398.000016210872,"st":47.0000019143492,"bm":0},{"ddd":0,"ind":29,"ty":4,"nm":"Shape Layer 11","parent":31,"sr":1,"ks":{"o":{"a":0,"k":100,"ix":11},"r":{"a":0,"k":11,"ix":10},"p":{"s":true,"x":{"a":1,"k":[{"i":{"x":[0.991],"y":[1]},"o":{"x":[0.009],"y":[0]},"n":["0p991_1_0p009_0"],"t":180,"s":[70.295],"e":[70.295]},{"t":213.000008675668}],"ix":3},"y":{"a":1,"k":[{"i":{"x":[0.423],"y":[1]},"o":{"x":[0.799],"y":[0]},"n":["0p423_1_0p799_0"],"t":196.436,"s":[61.621],"e":[-24.379]},{"t":229.43625934513}],"ix":4}},"a":{"a":0,"k":[0,0,0],"ix":1},"s":{"a":0,"k":[67.875,67.875,100],"ix":6}},"ao":0,"shapes":[{"ty":"gr","it":[{"ind":0,"ty":"sh","ix":1,"ks":{"a":0,"k":{"i":[[0,0],[6.832,-16.268],[0,0],[-11.514,27.955]],"o":[[0,0],[-6.242,14.861],[0,0],[11.514,-27.955]],"v":[[-62.579,153.616],[-80.735,173.435],[-84.572,211.508],[-58.631,193.553]],"c":true},"ix":2},"nm":"Path 1","mn":"ADBE Vector Shape - Group","hd":false},{"ty":"st","c":{"a":0,"k":[1,1,1,1],"ix":3},"o":{"a":0,"k":100,"ix":4},"w":{"a":0,"k":0,"ix":5},"lc":1,"lj":1,"ml":4,"ml2":{"a":0,"k":4,"ix":8},"bm":0,"nm":"Stroke 1","mn":"ADBE Vector Graphic - Stroke","hd":false},{"ty":"fl","c":{"a":0,"k":[0.956862807274,0.886274576187,0.800000071526,1],"ix":4},"o":{"a":0,"k":100,"ix":5},"r":1,"bm":0,"nm":"Fill 1","mn":"ADBE Vector Graphic - Fill","hd":false},{"ty":"tr","p":{"a":0,"k":[0,0],"ix":2},"a":{"a":0,"k":[0,0],"ix":1},"s":{"a":0,"k":[100,100],"ix":3},"r":{"a":0,"k":0,"ix":6},"o":{"a":0,"k":100,"ix":7},"sk":{"a":0,"k":0,"ix":4},"sa":{"a":0,"k":0,"ix":5},"nm":"Transform"}],"nm":"Shape 2","np":3,"cix":2,"bm":0,"ix":1,"mn":"ADBE Vector Group","hd":false},{"ty":"gr","it":[{"ind":0,"ty":"sh","ix":1,"ks":{"a":0,"k":{"i":[[0,0],[0,0],[-11.485,41.355]],"o":[[0,0],[0,0],[12.766,-45.968]],"v":[[-84.751,138.462],[-102.145,222.4],[-41.332,193.727]],"c":true},"ix":2},"nm":"Path 1","mn":"ADBE Vector Shape - Group","hd":false},{"ty":"st","c":{"a":0,"k":[1,1,1,1],"ix":3},"o":{"a":0,"k":100,"ix":4},"w":{"a":0,"k":0,"ix":5},"lc":1,"lj":1,"ml":4,"ml2":{"a":0,"k":4,"ix":8},"bm":0,"nm":"Stroke 1","mn":"ADBE Vector Graphic - Stroke","hd":false},{"ty":"fl","c":{"a":0,"k":[0.807843208313,0.662745118141,0.490196108818,1],"ix":4},"o":{"a":0,"k":100,"ix":5},"r":1,"bm":0,"nm":"Fill 1","mn":"ADBE Vector Graphic - Fill","hd":false},{"ty":"tr","p":{"a":0,"k":[0,0],"ix":2},"a":{"a":0,"k":[0,0],"ix":1},"s":{"a":0,"k":[100,100],"ix":3},"r":{"a":0,"k":0,"ix":6},"o":{"a":0,"k":100,"ix":7},"sk":{"a":0,"k":0,"ix":4},"sa":{"a":0,"k":0,"ix":5},"nm":"Transform"}],"nm":"Shape 1","np":3,"cix":2,"bm":0,"ix":2,"mn":"ADBE Vector Group","hd":false}],"ip":34.0000013848484,"op":360.000014663101,"st":0,"bm":0},{"ddd":0,"ind":30,"ty":4,"nm":"LockHead Outlines 17","parent":29,"sr":1,"ks":{"o":{"a":0,"k":100,"ix":11},"r":{"a":0,"k":197,"ix":10},"p":{"s":true,"x":{"a":0,"k":152.219,"ix":3},"y":{"a":0,"k":226.424,"ix":4}},"a":{"a":0,"k":[57.643,51.767,0],"ix":1},"s":{"a":0,"k":[757.417,757.417,100],"ix":6}},"ao":0,"shapes":[{"ty":"gr","it":[{"ind":0,"ty":"sh","ix":1,"ks":{"a":0,"k":{"i":[[0.82,0],[0,0],[0,3.678],[-0.479,0.068],[0,0],[0,-3.679]],"o":[[0,0],[-0.594,-0.046],[0,-3.679],[0,0],[0.82,0],[0,3.678]],"v":[[10.805,6.688],[10.458,6.709],[10.189,0.124],[10.458,-6.667],[10.805,-6.688],[12.296,0]],"c":true},"ix":2},"nm":"Path 1","mn":"ADBE Vector Shape - Group","hd":false},{"ty":"fl","c":{"a":0,"k":[0.749601721764,0.617707014084,0.459406644106,1],"ix":4},"o":{"a":0,"k":100,"ix":5},"r":1,"bm":0,"nm":"Fill 1","mn":"ADBE Vector Graphic - Fill","hd":false},{"ty":"tr","p":{"a":0,"k":[55.407,56.445],"ix":2},"a":{"a":0,"k":[0,0],"ix":1},"s":{"a":0,"k":[80.304,24.632],"ix":3},"r":{"a":0,"k":0,"ix":6},"o":{"a":0,"k":100,"ix":7},"sk":{"a":0,"k":0,"ix":4},"sa":{"a":0,"k":0,"ix":5},"nm":"Transform"}],"nm":"Group 8","np":2,"cix":2,"bm":0,"ix":1,"mn":"ADBE Vector Group","hd":false},{"ty":"gr","it":[{"ind":0,"ty":"sh","ix":1,"ks":{"a":0,"k":{"i":[[0.82,0],[0,0],[0,3.678],[-0.479,0.068],[0,0],[0,-3.679]],"o":[[0,0],[-0.594,-0.046],[0,-3.679],[0,0],[0.82,0],[0,3.678]],"v":[[4.968,6.688],[4.622,6.709],[4.352,0.124],[4.622,-6.667],[4.968,-6.688],[6.459,0]],"c":true},"ix":2},"nm":"Path 1","mn":"ADBE Vector Shape - Group","hd":false},{"ty":"fl","c":{"a":0,"k":[1,0.969330787659,0.93252146244,1],"ix":4},"o":{"a":0,"k":100,"ix":5},"r":1,"bm":0,"nm":"Fill 1","mn":"ADBE Vector Graphic - Fill","hd":false},{"ty":"tr","p":{"a":0,"k":[69.575,55.358],"ix":2},"a":{"a":0,"k":[0,0],"ix":1},"s":{"a":0,"k":[80.304,35.425],"ix":3},"r":{"a":0,"k":0,"ix":6},"o":{"a":0,"k":100,"ix":7},"sk":{"a":0,"k":0,"ix":4},"sa":{"a":0,"k":0,"ix":5},"nm":"Transform"}],"nm":"Group 6","np":2,"cix":2,"bm":0,"ix":2,"mn":"ADBE Vector Group","hd":false},{"ty":"gr","it":[{"ind":0,"ty":"sh","ix":1,"ks":{"a":0,"k":{"i":[[3.679,0],[0,0],[0,3.678],[-2.147,0.068],[0,0],[0.034,-5.035]],"o":[[0,0],[-2.664,-0.046],[0,-3.679],[0,0],[3.679,0],[-0.031,4.662]],"v":[[7.101,6.688],[5.548,6.709],[4.338,0.124],[5.548,-6.667],[6.806,-6.684],[13.494,0.004]],"c":true},"ix":2},"nm":"Path 1","mn":"ADBE Vector Shape - Group","hd":false},{"ty":"fl","c":{"a":0,"k":[0.956188738346,0.885867238045,0.801467180252,1],"ix":4},"o":{"a":0,"k":100,"ix":5},"r":1,"bm":0,"nm":"Fill 1","mn":"ADBE Vector Graphic - Fill","hd":false},{"ty":"tr","p":{"a":0,"k":[67.956,54.651],"ix":2},"a":{"a":0,"k":[0,0],"ix":1},"s":{"a":0,"k":[95.696,53.993],"ix":3},"r":{"a":0,"k":0,"ix":6},"o":{"a":0,"k":100,"ix":7},"sk":{"a":0,"k":0,"ix":4},"sa":{"a":0,"k":0,"ix":5},"nm":"Transform"}],"nm":"Group 5","np":2,"cix":2,"bm":0,"ix":3,"mn":"ADBE Vector Group","hd":false},{"ty":"gr","it":[{"ind":0,"ty":"sh","ix":1,"ks":{"a":0,"k":{"i":[[3.679,0],[0,0],[1.321,3.19],[-3.678,0],[-6.583,-0.372],[0,0],[0,-3.679]],"o":[[0,0],[-3.678,0],[-1.408,-3.399],[0,0],[6.583,0.372],[3.679,0],[0,3.678]],"v":[[5.759,6.267],[-14.52,6.641],[-22.041,0.796],[-6.523,-14.816],[-3.849,-3.998],[5.082,-3.53],[13.292,1.516]],"c":true},"ix":2},"nm":"Path 1","mn":"ADBE Vector Shape - Group","hd":false},{"ty":"fl","c":{"a":0,"k":[0.809206485748,0.663973331451,0.489664137363,1],"ix":4},"o":{"a":0,"k":100,"ix":5},"r":1,"bm":0,"nm":"Fill 1","mn":"ADBE Vector Graphic - Fill","hd":false},{"ty":"tr","p":{"a":0,"k":[67.846,51.76],"ix":2},"a":{"a":0,"k":[0,0],"ix":1},"s":{"a":0,"k":[100,100],"ix":3},"r":{"a":0,"k":0,"ix":6},"o":{"a":0,"k":100,"ix":7},"sk":{"a":0,"k":0,"ix":4},"sa":{"a":0,"k":0,"ix":5},"nm":"Transform"}],"nm":"Group 4","np":2,"cix":2,"bm":0,"ix":4,"mn":"ADBE Vector Group","hd":false}],"ip":34.0000013848484,"op":360.000014663101,"st":0,"bm":0},{"ddd":0,"ind":31,"ty":4,"nm":"Pin Outlines","parent":23,"sr":1,"ks":{"o":{"a":0,"k":100,"ix":11},"r":{"a":0,"k":0,"ix":10},"p":{"s":true,"x":{"a":1,"k":[{"i":{"x":[0.981],"y":[1]},"o":{"x":[0.019],"y":[0]},"n":["0p981_1_0p019_0"],"t":224,"s":[94.515],"e":[94.515]},{"t":240.0000097754}],"ix":3},"y":{"a":1,"k":[{"i":{"x":[0.105],"y":[1]},"o":{"x":[0.167],"y":[0.167]},"n":["0p105_1_0p167_0p167"],"t":242.598,"s":[153.899],"e":[214.899]},{"t":270.000010997325}],"ix":4}},"a":{"a":0,"k":[70,119,0],"ix":1},"s":{"a":0,"k":[70.141,70.141,100],"ix":6}},"ao":0,"shapes":[{"ty":"gr","it":[{"ind":0,"ty":"sh","ix":1,"ks":{"a":0,"k":{"i":[[0.778,0],[0,0],[0,0],[0,0],[0,-0.779],[0,0],[0,0],[0,0],[0,0],[0,0.779]],"o":[[0,0],[0,0],[0,0],[-0.778,0],[0,0.779],[0,0],[0,0],[0,0],[0,0],[0,-0.779]],"v":[[8.54,-1.407],[5.837,-1.407],[-5.835,-1.407],[-8.54,-1.407],[-8.201,0],[-8.111,1.407],[-5.835,1.407],[5.837,1.407],[8.111,1.407],[8.202,0]],"c":true},"ix":2},"nm":"Path 1","mn":"ADBE Vector Shape - Group","hd":false},{"ty":"fl","c":{"a":0,"k":[0.497999991623,0.497999991623,0.497999991623,1],"ix":4},"o":{"a":0,"k":100,"ix":5},"r":1,"bm":0,"nm":"Fill 1","mn":"ADBE Vector Graphic - Fill","hd":false},{"ty":"tr","p":{"a":0,"k":[26.788,30.303],"ix":2},"a":{"a":0,"k":[0,0],"ix":1},"s":{"a":0,"k":[100,100],"ix":3},"r":{"a":0,"k":0,"ix":6},"o":{"a":0,"k":100,"ix":7},"sk":{"a":0,"k":0,"ix":4},"sa":{"a":0,"k":0,"ix":5},"nm":"Transform"}],"nm":"Group 1","np":2,"cix":2,"bm":0,"ix":1,"mn":"ADBE Vector Group","hd":false},{"ty":"gr","it":[{"ind":0,"ty":"sh","ix":1,"ks":{"a":0,"k":{"i":[[0,-0.778],[0.778,0],[0,0],[0,0.778],[-0.779,0],[0,0]],"o":[[0,0.778],[0,0],[-0.779,0],[0,-0.778],[0,0],[0.778,0]],"v":[[6.725,0],[5.318,1.407],[-5.317,1.407],[-6.725,0],[-5.317,-1.407],[5.318,-1.407]],"c":true},"ix":2},"nm":"Path 1","mn":"ADBE Vector Shape - Group","hd":false},{"ty":"fl","c":{"a":0,"k":[0.847000002394,0.847000002394,0.847000002394,1],"ix":4},"o":{"a":0,"k":100,"ix":5},"r":1,"bm":0,"nm":"Fill 1","mn":"ADBE Vector Graphic - Fill","hd":false},{"ty":"tr","p":{"a":0,"k":[27.306,4.946],"ix":2},"a":{"a":0,"k":[0,0],"ix":1},"s":{"a":0,"k":[100,100],"ix":3},"r":{"a":0,"k":0,"ix":6},"o":{"a":0,"k":100,"ix":7},"sk":{"a":0,"k":0,"ix":4},"sa":{"a":0,"k":0,"ix":5},"nm":"Transform"}],"nm":"Group 2","np":2,"cix":2,"bm":0,"ix":2,"mn":"ADBE Vector Group","hd":false},{"ty":"gr","it":[{"ind":0,"ty":"sh","ix":1,"ks":{"a":0,"k":{"i":[[0,0],[-0.045,4.596],[3.174,0],[0,0],[0,0],[0,0],[0,-2.644],[-0.104,-4.205]],"o":[[0.111,-4.38],[0,-2.644],[0,0],[0,0],[0,0],[-3.174,0],[0.043,4.403],[0,0]],"v":[[26.774,5.268],[26.791,-0.46],[21.02,-5.268],[3.657,-5.268],[-3.75,-5.268],[-21.113,-5.268],[-26.884,-0.46],[-26.811,5.143]],"c":false},"ix":2},"nm":"Path 1","mn":"ADBE Vector Shape - Group","hd":false},{"ty":"fl","c":{"a":0,"k":[0,0,0,1],"ix":4},"o":{"a":0,"k":100,"ix":5},"r":1,"bm":0,"nm":"Fill 1","mn":"ADBE Vector Graphic - Fill","hd":false},{"ty":"tr","p":{"a":0,"k":[26.885,50.905],"ix":2},"a":{"a":0,"k":[0,0],"ix":1},"s":{"a":0,"k":[100,100],"ix":3},"r":{"a":0,"k":0,"ix":6},"o":{"a":0,"k":100,"ix":7},"sk":{"a":0,"k":0,"ix":4},"sa":{"a":0,"k":0,"ix":5},"nm":"Transform"}],"nm":"Group 3","np":4,"cix":2,"bm":0,"ix":3,"mn":"ADBE Vector Group","hd":false},{"ty":"gr","it":[{"ind":0,"ty":"sh","ix":1,"ks":{"a":0,"k":{"i":[[0,0],[10.195,19.88],[0.939,25.768],[0,0],[0,2.913],[-0.221,22.793],[3.174,0],[0,0],[0,0],[0,0],[0,-2.644],[-2.897,-14.088],[-3.497,0],[0,0],[-11.017,-21.478],[-25.999,0],[0,0],[0,0]],"o":[[-16.149,0],[-9.05,-17.641],[0,0],[3.497,0],[2.897,-14.088],[0,-2.644],[0,0],[0,0],[0,0],[-3.173,0],[0.222,22.793],[0,2.913],[0,0],[0.955,30.163],[14.616,28.495],[0,0],[0,0],[0,0]],"v":[[25.849,69.555],[-13.855,39.594],[-29.37,-28.171],[-26.419,-28.171],[-20.061,-33.466],[-16.036,-90.909],[-21.807,-95.715],[-39.171,-95.715],[-46.577,-95.715],[-63.941,-95.715],[-69.712,-90.909],[-65.687,-33.466],[-59.329,-28.171],[-55.551,-28.171],[-37.135,51.531],[25.849,95.715],[69.712,95.715],[69.712,69.555]],"c":true},"ix":2},"nm":"Path 1","mn":"ADBE Vector Shape - Group","hd":false},{"ty":"fl","c":{"a":0,"k":[0.109803922474,0.109803922474,0.109803922474,1],"ix":4},"o":{"a":0,"k":100,"ix":5},"r":1,"bm":0,"nm":"Fill 1","mn":"ADBE Vector Graphic - Fill","hd":false},{"ty":"tr","p":{"a":0,"k":[69.712,141.354],"ix":2},"a":{"a":0,"k":[0,0],"ix":1},"s":{"a":0,"k":[100,100],"ix":3},"r":{"a":0,"k":0,"ix":6},"o":{"a":0,"k":100,"ix":7},"sk":{"a":0,"k":0,"ix":4},"sa":{"a":0,"k":0,"ix":5},"nm":"Transform"}],"nm":"Group 4","np":2,"cix":2,"bm":0,"ix":4,"mn":"ADBE Vector Group","hd":false},{"ty":"gr","it":[{"ind":0,"ty":"sh","ix":1,"ks":{"a":0,"k":{"i":[[0.442,1.05],[1.277,2.085],[2.261,0],[0,0],[1.199,-1.869],[0.883,-2.206],[0,-1.102],[0,0],[-2.69,0],[0,0],[0,-1.184],[0,0],[-3.581,-0.96],[0,5.198],[0,0],[-1.184,0],[0,0],[0,2.689],[0,0]],"o":[[-0.906,-2.152],[-1.182,-1.928],[0,0],[-2.22,0],[-1.33,2.07],[-0.41,1.023],[0,0],[0,2.689],[0,0],[1.184,0],[0,0],[0,3.708],[5.417,1.454],[0,0],[0,-1.184],[0,0],[2.689,0],[0,0],[0,-1.14]],"v":[[15.622,-42.767],[12.476,-49.665],[6.926,-52.752],[-6.895,-52.752],[-12.38,-49.762],[-15.665,-42.811],[-16.283,-39.604],[-16.283,-29.062],[-11.393,-24.173],[-10.285,-24.173],[-8.141,-22.029],[-8.141,43.167],[-2.212,51.298],[8.143,43.453],[8.143,-22.029],[10.286,-24.173],[11.394,-24.173],[16.284,-29.062],[16.284,-39.458]],"c":true},"ix":2},"nm":"Path 1","mn":"ADBE Vector Shape - Group","hd":false},{"ty":"fl","c":{"a":0,"k":[0.647000002394,0.647000002394,0.647000002394,1],"ix":4},"o":{"a":0,"k":100,"ix":5},"r":1,"bm":0,"nm":"Fill 1","mn":"ADBE Vector Graphic - Fill","hd":false},{"ty":"tr","p":{"a":0,"k":[26.758,52.752],"ix":2},"a":{"a":0,"k":[0,0],"ix":1},"s":{"a":0,"k":[100,100],"ix":3},"r":{"a":0,"k":0,"ix":6},"o":{"a":0,"k":100,"ix":7},"sk":{"a":0,"k":0,"ix":4},"sa":{"a":0,"k":0,"ix":5},"nm":"Transform"}],"nm":"Group 5","np":2,"cix":2,"bm":0,"ix":5,"mn":"ADBE Vector Group","hd":false}],"ip":0,"op":398.000016210872,"st":0,"bm":0},{"ddd":0,"ind":32,"ty":4,"nm":"LockHead Outlines 18","parent":29,"sr":1,"ks":{"o":{"a":0,"k":100,"ix":11},"r":{"a":0,"k":198,"ix":10},"p":{"s":true,"x":{"a":0,"k":30.049,"ix":3},"y":{"a":0,"k":289.958,"ix":4}},"a":{"a":0,"k":[57.643,51.767,0],"ix":1},"s":{"a":0,"k":[707.649,707.649,100],"ix":6}},"ao":0,"shapes":[{"ty":"gr","it":[{"ind":0,"ty":"sh","ix":1,"ks":{"a":0,"k":{"i":[[3.679,0],[0,0],[0,3.678],[-3.678,0],[0,0],[0.278,-4.429]],"o":[[0,0],[-3.678,0],[0,-3.679],[0,0],[3.679,0],[-0.297,4.738]],"v":[[5.759,6.267],[-14.52,6.641],[-18.24,-0.016],[-14.52,-6.735],[10.491,-6.122],[17.091,1.577]],"c":true},"ix":2},"nm":"Path 1","mn":"ADBE Vector Shape - Group","hd":false},{"ty":"fl","c":{"a":0,"k":[0.638572275639,0.494655996561,0.321927279234,1],"ix":4},"o":{"a":0,"k":100,"ix":5},"r":1,"bm":0,"nm":"Fill 1","mn":"ADBE Vector Graphic - Fill","hd":false},{"ty":"tr","p":{"a":0,"k":[56.296,51.404],"ix":2},"a":{"a":0,"k":[0,0],"ix":1},"s":{"a":0,"k":[133.654,100],"ix":3},"r":{"a":0,"k":0,"ix":6},"o":{"a":0,"k":100,"ix":7},"sk":{"a":0,"k":0,"ix":4},"sa":{"a":0,"k":0,"ix":5},"nm":"Transform"}],"nm":"Group 9","np":2,"cix":2,"bm":0,"ix":1,"mn":"ADBE Vector Group","hd":false}],"ip":34.0000013848484,"op":360.000014663101,"st":0,"bm":0},{"ddd":0,"ind":33,"ty":4,"nm":"LockHead Outlines 16","parent":29,"sr":1,"ks":{"o":{"a":0,"k":100,"ix":11},"r":{"a":0,"k":198,"ix":10},"p":{"s":true,"x":{"a":0,"k":16.713,"ix":3},"y":{"a":0,"k":214.286,"ix":4}},"a":{"a":0,"k":[57.643,51.767,0],"ix":1},"s":{"a":0,"k":[707.649,707.649,100],"ix":6}},"ao":0,"shapes":[{"ty":"gr","it":[{"ind":0,"ty":"sh","ix":1,"ks":{"a":0,"k":{"i":[[0.82,0],[0,0],[0,3.678],[-0.479,0.068],[0,0],[0,-3.679]],"o":[[0,0],[-0.594,-0.046],[0,-3.679],[0,0],[0.82,0],[0,3.678]],"v":[[4.968,6.688],[4.622,6.709],[4.352,0.124],[4.622,-6.667],[4.968,-6.688],[6.459,0]],"c":true},"ix":2},"nm":"Path 1","mn":"ADBE Vector Shape - Group","hd":false},{"ty":"fl","c":{"a":0,"k":[0.749601721764,0.617707014084,0.459406644106,1],"ix":4},"o":{"a":0,"k":100,"ix":5},"r":1,"bm":0,"nm":"Fill 1","mn":"ADBE Vector Graphic - Fill","hd":false},{"ty":"tr","p":{"a":0,"k":[57.028,51.711],"ix":2},"a":{"a":0,"k":[0,0],"ix":1},"s":{"a":0,"k":[80.304,64.826],"ix":3},"r":{"a":0,"k":0,"ix":6},"o":{"a":0,"k":100,"ix":7},"sk":{"a":0,"k":0,"ix":4},"sa":{"a":0,"k":0,"ix":5},"nm":"Transform"}],"nm":"Group 8","np":2,"cix":2,"bm":0,"ix":1,"mn":"ADBE Vector Group","hd":false},{"ty":"gr","it":[{"ind":0,"ty":"sh","ix":1,"ks":{"a":0,"k":{"i":[[3.679,0],[0,0],[0,3.678],[-3.678,0],[0,0],[0.278,-4.429]],"o":[[0,0],[-3.678,0],[0,-3.679],[0,0],[3.679,0],[-0.297,4.738]],"v":[[5.759,6.267],[-14.52,6.641],[-18.24,-0.016],[-14.52,-6.735],[10.491,-6.122],[11.465,0.192]],"c":true},"ix":2},"nm":"Path 1","mn":"ADBE Vector Shape - Group","hd":false},{"ty":"fl","c":{"a":0,"k":[0.638572275639,0.494655996561,0.321927279234,1],"ix":4},"o":{"a":0,"k":100,"ix":5},"r":1,"bm":0,"nm":"Fill 1","mn":"ADBE Vector Graphic - Fill","hd":false},{"ty":"tr","p":{"a":0,"k":[56.296,51.404],"ix":2},"a":{"a":0,"k":[0,0],"ix":1},"s":{"a":0,"k":[133.654,100],"ix":3},"r":{"a":0,"k":0,"ix":6},"o":{"a":0,"k":100,"ix":7},"sk":{"a":0,"k":0,"ix":4},"sa":{"a":0,"k":0,"ix":5},"nm":"Transform"}],"nm":"Group 9","np":2,"cix":2,"bm":0,"ix":2,"mn":"ADBE Vector Group","hd":false},{"ty":"gr","it":[{"ind":0,"ty":"sh","ix":1,"ks":{"a":0,"k":{"i":[[3.679,0],[0,0],[0,3.678],[-3.678,0],[0,0],[0.278,-4.429]],"o":[[0,0],[-3.678,0],[0,-3.679],[0,0],[3.679,0],[-0.297,4.738]],"v":[[5.759,6.267],[-14.52,6.641],[-18.24,-0.016],[-14.52,-6.735],[5.759,-6.261],[11.465,0.192]],"c":true},"ix":2},"nm":"Path 1","mn":"ADBE Vector Shape - Group","hd":false},{"ty":"fl","c":{"a":0,"k":[0.809206485748,0.663973331451,0.489664137363,1],"ix":4},"o":{"a":0,"k":100,"ix":5},"r":1,"bm":0,"nm":"Fill 1","mn":"ADBE Vector Graphic - Fill","hd":false},{"ty":"tr","p":{"a":0,"k":[65.056,51.465],"ix":2},"a":{"a":0,"k":[0,0],"ix":1},"s":{"a":0,"k":[133.654,100],"ix":3},"r":{"a":0,"k":0,"ix":6},"o":{"a":0,"k":100,"ix":7},"sk":{"a":0,"k":0,"ix":4},"sa":{"a":0,"k":0,"ix":5},"nm":"Transform"}],"nm":"Group 4","np":2,"cix":2,"bm":0,"ix":3,"mn":"ADBE Vector Group","hd":false}],"ip":34.0000013848484,"op":360.000014663101,"st":0,"bm":0},{"ddd":0,"ind":34,"ty":4,"nm":"Shape Layer 8","parent":23,"sr":1,"ks":{"o":{"a":0,"k":100,"ix":11},"r":{"a":0,"k":0,"ix":10},"p":{"a":0,"k":[112.5,-179.182,0],"ix":2},"a":{"a":0,"k":[0,0,0],"ix":1},"s":{"a":0,"k":[71.94,71.94,100],"ix":6}},"ao":0,"shapes":[{"ty":"gr","it":[{"ty":"rc","d":1,"s":{"a":0,"k":[230.312,602.75],"ix":2},"p":{"a":0,"k":[0,0],"ix":3},"r":{"a":0,"k":0,"ix":4},"nm":"Rectangle Path 1","mn":"ADBE Vector Shape - Rect","hd":false},{"ty":"fl","c":{"a":0,"k":[0.707276344299,0.707276344299,0.707276344299,1],"ix":4},"o":{"a":0,"k":100,"ix":5},"r":1,"bm":0,"nm":"Fill 1","mn":"ADBE Vector Graphic - Fill","hd":false},{"ty":"tr","p":{"a":0,"k":[88.156,6.375],"ix":2},"a":{"a":0,"k":[0,0],"ix":1},"s":{"a":0,"k":[100,100],"ix":3},"r":{"a":0,"k":0,"ix":6},"o":{"a":0,"k":100,"ix":7},"sk":{"a":0,"k":0,"ix":4},"sa":{"a":0,"k":0,"ix":5},"nm":"Transform"}],"nm":"Rectangle 1","np":2,"cix":2,"bm":0,"ix":1,"mn":"ADBE Vector Group","hd":false},{"ty":"gr","it":[{"d":1,"ty":"el","s":{"a":0,"k":[478.984,478.984],"ix":2},"p":{"a":0,"k":[0,0],"ix":3},"nm":"Ellipse Path 1","mn":"ADBE Vector Shape - Ellipse","hd":false},{"ty":"fl","c":{"a":0,"k":[0.937254905701,0.937254905701,0.937254905701,1],"ix":4},"o":{"a":0,"k":100,"ix":5},"r":1,"bm":0,"nm":"Fill 1","mn":"ADBE Vector Graphic - Fill","hd":false},{"ty":"tr","p":{"a":0,"k":[-0.094,-2.723],"ix":2},"a":{"a":0,"k":[0,0],"ix":1},"s":{"a":0,"k":[100,100],"ix":3},"r":{"a":0,"k":0,"ix":6},"o":{"a":0,"k":100,"ix":7},"sk":{"a":0,"k":0,"ix":4},"sa":{"a":0,"k":0,"ix":5},"nm":"Transform"}],"nm":"Ellipse 1","np":2,"cix":2,"bm":0,"ix":2,"mn":"ADBE Vector Group","hd":false}],"ip":-3.00000012219251,"op":398.000016210872,"st":38.0000015477717,"bm":0},{"ddd":0,"ind":35,"ty":4,"nm":"Shape Layer 9","parent":23,"sr":1,"ks":{"o":{"a":0,"k":100,"ix":11},"r":{"a":0,"k":0,"ix":10},"p":{"a":0,"k":[112.5,57.5,0],"ix":2},"a":{"a":0,"k":[0,0,0],"ix":1},"s":{"a":0,"k":[71.94,71.94,100],"ix":6}},"ao":0,"shapes":[{"ty":"gr","it":[{"ty":"rc","d":1,"s":{"a":0,"k":[230.312,602.75],"ix":2},"p":{"a":0,"k":[0,0],"ix":3},"r":{"a":0,"k":0,"ix":4},"nm":"Rectangle Path 1","mn":"ADBE Vector Shape - Rect","hd":false},{"ty":"fl","c":{"a":0,"k":[0.707276344299,0.707276344299,0.707276344299,1],"ix":4},"o":{"a":0,"k":100,"ix":5},"r":1,"bm":0,"nm":"Fill 1","mn":"ADBE Vector Graphic - Fill","hd":false},{"ty":"tr","p":{"a":0,"k":[88.156,6.375],"ix":2},"a":{"a":0,"k":[0,0],"ix":1},"s":{"a":0,"k":[100,100],"ix":3},"r":{"a":0,"k":0,"ix":6},"o":{"a":0,"k":100,"ix":7},"sk":{"a":0,"k":0,"ix":4},"sa":{"a":0,"k":0,"ix":5},"nm":"Transform"}],"nm":"Rectangle 1","np":2,"cix":2,"bm":0,"ix":1,"mn":"ADBE Vector Group","hd":false},{"ty":"gr","it":[{"d":1,"ty":"el","s":{"a":0,"k":[478.984,478.984],"ix":2},"p":{"a":0,"k":[0,0],"ix":3},"nm":"Ellipse Path 1","mn":"ADBE Vector Shape - Ellipse","hd":false},{"ty":"fl","c":{"a":0,"k":[0.937254905701,0.937254905701,0.937254905701,1],"ix":4},"o":{"a":0,"k":100,"ix":5},"r":1,"bm":0,"nm":"Fill 1","mn":"ADBE Vector Graphic - Fill","hd":false},{"ty":"tr","p":{"a":0,"k":[-0.094,-2.723],"ix":2},"a":{"a":0,"k":[0,0],"ix":1},"s":{"a":0,"k":[100,100],"ix":3},"r":{"a":0,"k":0,"ix":6},"o":{"a":0,"k":100,"ix":7},"sk":{"a":0,"k":0,"ix":4},"sa":{"a":0,"k":0,"ix":5},"nm":"Transform"}],"nm":"Ellipse 1","np":2,"cix":2,"bm":0,"ix":2,"mn":"ADBE Vector Group","hd":false}],"ip":-3.00000012219251,"op":398.000016210872,"st":38.0000015477717,"bm":0},{"ddd":0,"ind":36,"ty":4,"nm":"Shape Layer 6","parent":23,"sr":1,"ks":{"o":{"a":0,"k":100,"ix":11},"r":{"a":0,"k":0,"ix":10},"p":{"a":0,"k":[112.5,57.5,0],"ix":2},"a":{"a":0,"k":[0,0,0],"ix":1},"s":{"a":0,"k":[71.94,71.94,100],"ix":6}},"ao":0,"shapes":[{"ty":"gr","it":[{"ty":"rc","d":1,"s":{"a":0,"k":[230.312,602.75],"ix":2},"p":{"a":0,"k":[0,0],"ix":3},"r":{"a":0,"k":0,"ix":4},"nm":"Rectangle Path 1","mn":"ADBE Vector Shape - Rect","hd":false},{"ty":"fl","c":{"a":0,"k":[0.707276344299,0.707276344299,0.707276344299,1],"ix":4},"o":{"a":0,"k":100,"ix":5},"r":1,"bm":0,"nm":"Fill 1","mn":"ADBE Vector Graphic - Fill","hd":false},{"ty":"tr","p":{"a":0,"k":[88.156,6.375],"ix":2},"a":{"a":0,"k":[0,0],"ix":1},"s":{"a":0,"k":[100,100],"ix":3},"r":{"a":0,"k":0,"ix":6},"o":{"a":0,"k":100,"ix":7},"sk":{"a":0,"k":0,"ix":4},"sa":{"a":0,"k":0,"ix":5},"nm":"Transform"}],"nm":"Rectangle 1","np":2,"cix":2,"bm":0,"ix":1,"mn":"ADBE Vector Group","hd":false},{"ty":"gr","it":[{"d":1,"ty":"el","s":{"a":0,"k":[478.984,478.984],"ix":2},"p":{"a":0,"k":[0,0],"ix":3},"nm":"Ellipse Path 1","mn":"ADBE Vector Shape - Ellipse","hd":false},{"ty":"fl","c":{"a":0,"k":[0.937254905701,0.937254905701,0.937254905701,1],"ix":4},"o":{"a":0,"k":100,"ix":5},"r":1,"bm":0,"nm":"Fill 1","mn":"ADBE Vector Graphic - Fill","hd":false},{"ty":"tr","p":{"a":0,"k":[-0.094,-2.723],"ix":2},"a":{"a":0,"k":[0,0],"ix":1},"s":{"a":0,"k":[100,100],"ix":3},"r":{"a":0,"k":0,"ix":6},"o":{"a":0,"k":100,"ix":7},"sk":{"a":0,"k":0,"ix":4},"sa":{"a":0,"k":0,"ix":5},"nm":"Transform"}],"nm":"Ellipse 1","np":2,"cix":2,"bm":0,"ix":2,"mn":"ADBE Vector Group","hd":false}],"ip":-3.00000012219251,"op":398.000016210872,"st":38.0000015477717,"bm":0},{"ddd":0,"ind":37,"ty":1,"nm":"White Solid 6","sr":1,"ks":{"o":{"a":0,"k":100,"ix":11},"r":{"a":0,"k":0,"ix":10},"p":{"a":0,"k":[500,500,0],"ix":2},"a":{"a":0,"k":[500,500,0],"ix":1},"s":{"a":0,"k":[100,100,100],"ix":6}},"ao":0,"sw":1000,"sh":1000,"sc":"#efefef","ip":0,"op":750.000030548126,"st":0,"bm":0}]}],"layers":[{"ddd":0,"ind":1,"ty":0,"nm":"NEW_BTOOTH_UNLOCK","refId":"comp_0","sr":1,"ks":{"o":{"a":0,"k":100,"ix":11},"r":{"a":0,"k":0,"ix":10},"p":{"a":0,"k":[500,500,0],"ix":2},"a":{"a":0,"k":[500,500,0],"ix":1},"s":{"a":0,"k":[100,100,100],"ix":6}},"ao":0,"hasMask":true,"masksProperties":[{"inv":false,"mode":"a","pt":{"a":0,"k":{"i":[[255.891,0],[0,-255.891],[-255.891,0],[0,255.891]],"o":[[-255.891,0],[0,255.891],[255.891,0],[0,-255.891]],"v":[[503.332,28],[40,491.332],[503.332,954.664],[966.664,491.332]],"c":true},"ix":1},"o":{"a":0,"k":100,"ix":3},"x":{"a":0,"k":0,"ix":4},"nm":"Mask 1"}],"w":1000,"h":1000,"ip":0,"op":750.000030548126,"st":0,"bm":0}],"markers":[]}
